probador.v
module probadorbyte(
    output reg clk_f,
    output reg clk_2f,
    output reg [31:0] data_in,
    output reg valid_in,
    input [31:0] lane_0,
    input [31:0] lane_1,
    input valid_0,
    input valid_1);
	initial begin
	$dumpfile("probador.vcd");
	$dumpvars;

	
	{data_in} <= 32'h00000000;
    {valid_in} <= 1;


	@(posedge clk_2f);

    {valid_in} <= 1;
	data_in <= 32'hFFFFFFFF;

	@(posedge clk_2f);

    data_in <= 32'hEEEEEEEE;


    @(posedge clk_2f);
 
    data_in <= 32'hDDDDDDDD;

	@(posedge clk_2f);
	
    valid_in <=1;
    data_in <= 32'hCCCCCCCC;

      
    @(posedge clk_2f);
    valid_in <=0;
    data_in <= 32'hBBBBBBBB;

	@(posedge clk_2f);
	valid_in <=0;
    data_in <= 32'hAAAAAAAA;

 
 
	$finish;
	end
	
	//initial clk_4f <= 0;
	//always #1 clk_4f <= ~clk_4f;

	initial clk_2f <= 0;
	always #2 clk_2f <= ~clk_2f;

	initial clk_f <= 0;
	always #4 clk_f <= ~clk_f;


endmodule

byte_striping.v
module byte_strip(
    input clk_f,
    input clk_2f,
    input [31:0] data_in,
    input valid_in,
    output reg [31:0] lane_0,
    output reg [31:0] lane_1,
    output reg valid_0,
    output reg valid_1
);
initial begin
    lane_0<=32'h00000000;
    lane_1<=32'h00000000;
    valid_0 <= 1'b0;
    valid_1 <= 1'b0;

end
    always @(posedge clk_f ) 
        begin
            if (valid_in ==0) 
                begin
                    valid_0 <= 1'b0;
                    lane_0 <= 32'h00000000;
                    
                end 
            else 
                begin
                    valid_0 <= 1'b1;
                    lane_0 = data_in;

                    
                end
            
        end
    always @(negedge clk_f ) 
        begin
            if (valid_in ==0) 
                begin
                    valid_1 <= 1'b0;
                    lane_1 <= 32'h00000000;
                    
                end 
            else 
                begin
                    valid_1 <= 1'b1;
                    lane_1 = data_in;

                    
                end
            
        end
    


endmodule

BancoPrueba.v
`timescale 	1s				/ 1s
`include "byte_striping.v"
`include "probador.v"

module pruebas;


    wire clk_2f;
    wire clk_f;
    wire valid_in;
    wire valid_0;
    wire valid_1;
	
    wire [31:0] data_in;

    
    wire [31:0] lane_0;
    wire [31:0] lane_1;

		byte_strip byte_Str(/*AUTOINST*/
        //Outputs
        .lane_0 (lane_0[31:0]),
        .lane_1 (lane_1[31:0]),
        .valid_0 (valid_0),
        .valid_1 (valid_1),
		//Inputs
		.clk_f (clk_f),
        .clk_2f (clk_2f),
        .valid_in (valid_in),
        .data_in (data_in[31:0])
        );

		probadorbyte muxp(/*AUTOINS*/
		//Outputs
        .lane_0 (lane_0[31:0]),
        .lane_1 (lane_1[31:0]),
        .valid_0 (valid_0),
        .valid_1 (valid_1),
		//Inputs
		.clk_f (clk_f),
        .clk_2f (clk_2f),
        .valid_in (valid_in),
        .data_in (data_in[31:0]));
endmodule

probador.vcd
$date
	Thu Sep 30 20:02:12 2021
$end
$version
	Icarus Verilog
$end
$timescale
	1s
$end
$scope module pruebas $end
$var wire 1 ! valid_in $end
$var wire 1 " valid_1 $end
$var wire 1 # valid_0 $end
$var wire 32 $ lane_1 [31:0] $end
$var wire 32 % lane_0 [31:0] $end
$var wire 32 & data_in [31:0] $end
$var wire 1 ' clk_f $end
$var wire 1 ( clk_2f $end
$scope module byte_Str $end
$var wire 1 ! valid_in $end
$var wire 32 ) data_in [31:0] $end
$var wire 1 ' clk_f $end
$var wire 1 ( clk_2f $end
$var reg 32 * lane_0 [31:0] $end
$var reg 32 + lane_1 [31:0] $end
$var reg 1 # valid_0 $end
$var reg 1 " valid_1 $end
$upscope $end
$scope module muxp $end
$var wire 32 , lane_0 [31:0] $end
$var wire 32 - lane_1 [31:0] $end
$var wire 1 # valid_0 $end
$var wire 1 " valid_1 $end
$var reg 1 ( clk_2f $end
$var reg 1 ' clk_f $end
$var reg 32 . data_in [31:0] $end
$var reg 1 ! valid_in $end
$upscope $end
$upscope $end
$enddefinitions $end
#0
$dumpvars
b0 .
b0 -
b0 ,
b0 +
b0 *
b0 )
0(
0'
b0 &
b0 %
b0 $
0#
1"
1!
$end
#2
b11111111111111111111111111111111 &
b11111111111111111111111111111111 )
b11111111111111111111111111111111 .
1(
#4
1#
b11111111111111111111111111111111 %
b11111111111111111111111111111111 *
b11111111111111111111111111111111 ,
0(
1'
#6
b11101110111011101110111011101110 &
b11101110111011101110111011101110 )
b11101110111011101110111011101110 .
1(
#8
b11101110111011101110111011101110 $
b11101110111011101110111011101110 +
b11101110111011101110111011101110 -
0(
0'
#10
b11011101110111011101110111011101 &
b11011101110111011101110111011101 )
b11011101110111011101110111011101 .
1(
#12
b11011101110111011101110111011101 %
b11011101110111011101110111011101 *
b11011101110111011101110111011101 ,
0(
1'
#14
b11001100110011001100110011001100 &
b11001100110011001100110011001100 )
b11001100110011001100110011001100 .
1(
#16
b11001100110011001100110011001100 $
b11001100110011001100110011001100 +
b11001100110011001100110011001100 -
0(
0'
#18
b10111011101110111011101110111011 &
b10111011101110111011101110111011 )
b10111011101110111011101110111011 .
0!
1(
#20
b0 %
b0 *
b0 ,
0#
0(
1'
#22
b10101010101010101010101010101010 &
b10101010101010101010101010101010 )
b10101010101010101010101010101010 .
1(
