phy_tx/probador_phy_tx.v
// Fecha: 21-10-2021
// Probador del transmisor phy_tx
// Version 1.0

module probador_phy_tx(
    output reg clk_32f,
    output reg [31:0] data_in,
    output reg valid_in,
    input phy_tx_out_0,
    input phy_tx_out_1);

	initial clk_32f <= 0;
    reg clk = 0 ;
	always #1 clk_32f <= ~clk_32f;
    always #32 clk <= ~clk;


	initial begin
	$dumpfile("phy_tx.vcd");
	$dumpvars;

	
	{data_in} <= 32'h00000000;
    {valid_in} <= 1;


	@(posedge clk);

    {valid_in} <= 1;
	data_in <= 32'hFFFFFFFF;

	@(posedge clk);

    data_in <= 32'hEEEEEEEE;


    @(posedge clk);
 
    data_in <= 32'hDDDDDDDD;

	@(posedge clk);
	
    valid_in <=1;
    data_in <= 32'hCCCCCCCC;

      
    @(posedge clk);
    valid_in <=0;
    data_in <= 32'hBBBBBBBB;

	@(posedge clk);
	valid_in <=0;
    data_in <= 32'hAAAAAAAA;
 
	#15 $finish;
	end


endmodule

phy_tx/paralelo_serial.v
// Fecha: 20-10-2021
// Convertidor señal serial-paralelo
// Version 1.0

// Módulo con la lógica del convertidor de señales
module paralelo_serial (
    input clk_4f,
    input clk_32f,
    input valid_0,
    input [7:0] data_in,
    output reg data_out
);
    
    reg [7:0] data2send;            // Cable para almacenar la señal para la salida en 8 bits
    reg [2:0] contador = 3'b000;    // Contador para sincronizar salida data_out

    always @(posedge clk_4f) begin
    if (valid_0 == 1) begin
        data2send <= data_in;        // Asignar data_in a data2out
    end

    if (valid_0 == 0) begin
        data2send <= 8'hBC;         // En caso de que valid sea 0 se le asigna hex(BC)
    end

    end  

    

    always @(posedge clk_32f) begin         // Logica para convertir señal paralelo a serial
        case (contador)
            3'b100: data_out = data2send[7];
            3'b101: data_out = data2send[6];
            3'b110: data_out = data2send[5];
            3'b111: data_out = data2send[4];
            3'b000: data_out = data2send[3];
            3'b001: data_out = data2send[2];
            3'b010: data_out = data2send[1];
            3'b011: data_out = data2send[0];
            default: data_out = 1'b0;
        endcase
    
    contador = contador + 1;                // Aumentar el contador
    end


endmodule

phy_tx/conv_32_8.v
//Fecha: 04-10-2021
//Convertidor de 32 bits a 8 bits
//Version 1.0 

module conv_32_8 (input clk_4f, //senal de reloj
    input valid_in, //bit de entrada de validez
    input [31:0] data_in, //entrada de 32 bits
    output reg [7:0] data_out,//salida de 8 bits
    output reg valid_out); //bit de salida de validez

    reg [1:0] contador = 2'b00;//contador

    always @(posedge clk_4f) begin
    if (valid_in == 1) begin
      case (contador)
        2'b00: data_out = data_in[31:24];
        2'b01: data_out = data_in[23:16];
        2'b10: data_out = data_in[15:8];
        2'b11: data_out = data_in[7:0];
        default: data_out = 8'h00;
      endcase
      contador = contador + 1;
      valid_out <= valid_in;
      end
    else begin
        valid_out <= valid_in;
        contador = 2'b00;
    end
    end

endmodule

phy_tx/byte_striping.v
module byte_striping(
    input clk_f,
    input clk_2f,
    input [31:0] data_in,
    input valid_in,
    output reg [31:0] lane_0,
    output reg [31:0] lane_1,
    output reg valid_0,
    output reg valid_1
);
initial begin
    lane_0<=32'h00000000;
    lane_1<=32'h00000000;
    valid_0 <= 1'b0;
    valid_1 <= 1'b0;

end
    always @(posedge clk_f ) 
        begin
            if (valid_in ==0) 
                begin
                    valid_0 <= 1'b0;
                    lane_0 <= 32'h00000000;
                    
                end 
            else 
                begin
                    valid_0 <= 1'b1;
                    lane_0 = data_in;

                    
                end
            
        end
    always @(negedge clk_f ) 
        begin
            if (valid_in ==0) 
                begin
                    valid_1 <= 1'b0;
                    lane_1 <= 32'h00000000;
                    
                end 
            else 
                begin
                    valid_1 <= 1'b1;
                    lane_1 = data_in;

                    
                end
            
        end
    


endmodule

phy/clock_generator.v
module clock_generator(
    input clk_32f,
    output reg clk_f,
    output reg clk_2f,
    output reg clk_4f
    );

    initial clk_f <= 0;
    initial clk_2f <= 0;
    initial clk_4f <= 0;
    
    reg [27:0] counter1 = 28'd4;
    reg [27:0] counter2 = 28'd4;
    reg [27:0] counter3 = 28'd4;
    parameter df_1 = 28'd32; //divisor de frecuencia
    parameter df_2 = 28'd16; //divisor de frecuencia
    parameter df_4 = 28'd8; //divisor de frecuencia

    always @(posedge clk_32f)
    begin
      counter1<= counter1 + 28'd1;
        if (counter1 >=(df_1-1))
            counter1 <= 28'd0;
            clk_f <= (counter1 <df_1/2)?1'b1:1'b0;
    end

    always @(posedge clk_32f)
    begin
      counter2 <= counter2 + 28'd1;
        if (counter2 >=(df_2-1))
            counter2 <= 28'd0;
            clk_2f <= (counter2 <df_2/2)?1'b1:1'b0;
    end
    
    always @(posedge clk_32f)
    begin
      counter3 <= counter3 + 28'd1;
        if (counter3 >=(df_4-1))
            counter3 <= 28'd0;
            clk_4f <= (counter3 <df_4/2)?1'b1:1'b0;
    end

    
endmodule

phy_tx/phy_tx.v
// Fecha: 21-10-2021
// Modulo del transmisor phy_tx
// Version 1.0
`include "clock_generator.v"
`include "byte_striping.v"
`include "conv_32_8.v"
`include "paralelo_serial.v"


module phy_tx (input [31:0] data_in,
    input valid_in,
    input clk_32f,
    output phy_tx_out_0,
    output phy_tx_out_1);

    //Cables para salidas de modulo de clock_generator
    wire clk_2f, clk_4f, clk_32f;

    //Cables para salidas de modulo de byte_striping
    wire valid_0, valid_1;
    wire [31:0] lane_0;
    wire [31:0] lane_1;

    //Cables para salidas de modulos de conv_32_8
    wire [7:0] conv_32_8_out_0;
    wire conv_32_8_valid_0, conv_32_8_valid_1;
    wire [7:0] conv_32_8_out_1;

    clock_generator clock_generator(/*AUTOINST*/
				    // Outputs
				    .clk_f		(clk_f),
				    .clk_2f		(clk_2f),
				    .clk_4f		(clk_4f),
				    // Inputs
				    .clk_32f		(clk_32f));

    byte_striping byte_striping(/*AUTOINST*/
				// Outputs
				.lane_0		(lane_0[31:0]),
				.lane_1		(lane_1[31:0]),
				.valid_0	(valid_0),
				.valid_1	(valid_1),
				// Inputs
				.clk_f		(clk_f),
				.clk_2f		(clk_2f),
				.data_in	(data_in[31:0]),
				.valid_in	(valid_in));

    conv_32_8 conv_0(/*AUTOINST*/
		     // Outputs
		     .data_out		(conv_32_8_out_0),
		     .valid_out		(conv_32_8_valid_0),
		     // Inputs
		     .clk_4f		(clk_4f),
		     .valid_in		(valid_0),
		     .data_in		(lane_0));

    conv_32_8 conv_1(/*AUTOINST*/
		     // Outputs
		     .data_out		(conv_32_8_out_1),
		     .valid_out		(conv_32_8_valid_1),
		     // Inputs
		     .clk_4f		(clk_4f),
		     .valid_in		(valid_1),
		     .data_in		(lane_1));

    paralelo_serial sign_0(/*AUTOINST*/
			   // Outputs
			   .data_out		(phy_tx_out_0),
			   // Inputs
			   .clk_4f		(clk_4f),
			   .clk_32f		(clk_32f),
			   .valid_0		(conv_32_8_valid_0),
			   .data_in		(conv_32_8_out_0));

    paralelo_serial sign_1(/*AUTOINST*/
			   // Outputs
			   .data_out		(phy_tx_out_1),
			   // Inputs
			   .clk_4f		(clk_4f),
			   .clk_32f		(clk_32f),
			   .valid_0		(conv_32_8_valid_1),
			   .data_in		(conv_32_8_out_1));

    endmodule

phy_tx/banco_phy_tx.v
//Fecha: 21-10-2021
//Version 1.0

`timescale 	1ns	/ 100ps
// escala	unidad temporal (valor de "#1") / precisión

// includes de archivos de verilog
`include "phy_tx.v"
`include "probador_phy_tx.v"

module banco_phy_tx; // Testbench

    //Inputs
    wire clk_32f, valid_0;
    wire [31:0] data_in;

    //Outputs
	wire valid_out;
    wire phy_tx_out_0;
    wire phy_tx_out_1;

	// Se instancia el módulo del convertidor 32 a 8 bits conductual
	phy_tx phy_tx(/*AUTOINST*/
		      // Outputs
		      .phy_tx_out_0	(phy_tx_out_0),
		      .phy_tx_out_1	(phy_tx_out_1),
		      // Inputs
		      .data_in		(data_in[31:0]),
		      .valid_in		(valid_in),
		      .clk_32f		(clk_32f));

	// Probador: generador de señales y monitor
	probador_phy_tx probador_phy_tx(/*AUTOINST*/
					// Outputs
					.clk_32f		(clk_32f),
					.data_in	(data_in[31:0]),
					.valid_in	(valid_in),
					// Inputs
					.phy_tx_out_0	(phy_tx_out_0),
					.phy_tx_out_1	(phy_tx_out_1));

endmodule

phy_tx/phy_tx.vcd
$date
	Thu Oct 21 17:49:30 2021
$end
$version
	Icarus Verilog
$end
$timescale
	100ps
$end
$scope module banco_phy_tx $end
$var wire 1 ! valid_in $end
$var wire 1 " phy_tx_out_1 $end
$var wire 1 # phy_tx_out_0 $end
$var wire 32 $ data_in [31:0] $end
$var wire 1 % clk_32f $end
$scope module phy_tx $end
$var wire 1 ! valid_in $end
$var wire 1 & valid_1 $end
$var wire 1 ' valid_0 $end
$var wire 1 " phy_tx_out_1 $end
$var wire 1 # phy_tx_out_0 $end
$var wire 32 ( lane_1 [31:0] $end
$var wire 32 ) lane_0 [31:0] $end
$var wire 32 * data_in [31:0] $end
$var wire 1 + conv_32_8_valid_1 $end
$var wire 1 , conv_32_8_valid_0 $end
$var wire 8 - conv_32_8_out_1 [7:0] $end
$var wire 8 . conv_32_8_out_0 [7:0] $end
$var wire 1 / clk_f $end
$var wire 1 0 clk_4f $end
$var wire 1 % clk_32f $end
$var wire 1 1 clk_2f $end
$scope module byte_striping $end
$var wire 1 ! valid_in $end
$var wire 32 2 data_in [31:0] $end
$var wire 1 / clk_f $end
$var wire 1 1 clk_2f $end
$var reg 32 3 lane_0 [31:0] $end
$var reg 32 4 lane_1 [31:0] $end
$var reg 1 ' valid_0 $end
$var reg 1 & valid_1 $end
$upscope $end
$scope module clock_generator $end
$var wire 1 % clk_32f $end
$var reg 1 1 clk_2f $end
$var reg 1 0 clk_4f $end
$var reg 1 / clk_f $end
$var reg 28 5 counter1 [27:0] $end
$var reg 28 6 counter2 [27:0] $end
$var reg 28 7 counter3 [27:0] $end
$upscope $end
$scope module conv_0 $end
$var wire 1 0 clk_4f $end
$var wire 32 8 data_in [31:0] $end
$var wire 1 ' valid_in $end
$var reg 2 9 contador [1:0] $end
$var reg 8 : data_out [7:0] $end
$var reg 1 , valid_out $end
$upscope $end
$scope module conv_1 $end
$var wire 1 0 clk_4f $end
$var wire 32 ; data_in [31:0] $end
$var wire 1 & valid_in $end
$var reg 2 < contador [1:0] $end
$var reg 8 = data_out [7:0] $end
$var reg 1 + valid_out $end
$upscope $end
$scope module sign_0 $end
$var wire 1 0 clk_4f $end
$var wire 8 > data_in [7:0] $end
$var wire 1 , valid_0 $end
$var wire 1 % clk_32f $end
$var reg 3 ? contador [2:0] $end
$var reg 8 @ data2send [7:0] $end
$var reg 1 # data_out $end
$upscope $end
$scope module sign_1 $end
$var wire 1 0 clk_4f $end
$var wire 8 A data_in [7:0] $end
$var wire 1 + valid_0 $end
$var wire 1 % clk_32f $end
$var reg 3 B contador [2:0] $end
$var reg 8 C data2send [7:0] $end
$var reg 1 " data_out $end
$upscope $end
$upscope $end
$scope module probador_phy_tx $end
$var wire 1 # phy_tx_out_0 $end
$var wire 1 " phy_tx_out_1 $end
$var reg 1 D clk $end
$var reg 1 % clk_32f $end
$var reg 32 E data_in [31:0] $end
$var reg 1 ! valid_in $end
$upscope $end
$upscope $end
$enddefinitions $end
#0
$dumpvars
b0 E
0D
bx C
b0 B
bx A
bx @
b0 ?
bx >
bx =
b0 <
b0 ;
bx :
b0 9
b0 8
b100 7
b100 6
b100 5
b0 4
b0 3
b0 2
x1
x0
x/
bx .
bx -
x,
x+
b0 *
b0 )
b0 (
0'
0&
0%
b0 $
x#
x"
1!
$end
#10
1'
1/
b101 5
11
b101 6
00
b101 7
b1 ?
b1 B
1%
#20
0%
#30
b110 7
b110 6
b110 5
b10 B
b10 ?
1%
#40
0%
#50
b111 5
b111 6
b111 7
b11 ?
b11 B
1%
#60
0%
#70
b0 7
b1000 6
b1000 5
b100 B
b100 ?
1%
#80
0%
#90
1,
0+
b1 9
b0 .
b0 :
b0 >
b1001 5
01
b1001 6
10
b1 7
b101 ?
b101 B
1%
#100
0%
#110
b10 7
b1010 6
b1010 5
b110 B
b110 ?
1%
#120
0%
#130
b1011 5
b1011 6
b11 7
b111 ?
b111 B
1%
#140
0%
#150
b100 7
b1100 6
b1100 5
b0 B
b0 ?
1%
#160
0%
#170
b1101 5
b1101 6
00
b101 7
b1 ?
b1 B
1%
#180
0%
#190
b110 7
b1110 6
b1110 5
b10 B
b10 ?
1%
#200
0%
#210
b1111 5
b1111 6
b111 7
b11 ?
b11 B
1%
#220
0%
#230
b0 7
b0 6
b10000 5
b100 B
b100 ?
1%
#240
0%
#250
1&
b10111100 C
b0 @
b10 9
0/
b10001 5
11
b1 6
10
b1 7
b101 ?
b101 B
1%
#260
0%
#270
b10 7
b10 6
b10010 5
b110 B
0"
b110 ?
0#
1%
#280
0%
#290
b10011 5
b11 6
b11 7
b111 ?
b111 B
1"
1%
#300
0%
#310
b100 7
b100 6
b10100 5
b0 B
b0 ?
1%
#320
b11111111111111111111111111111111 $
b11111111111111111111111111111111 *
b11111111111111111111111111111111 2
b11111111111111111111111111111111 E
0%
1D
#330
b10101 5
b101 6
00
b101 7
b1 ?
b1 B
1%
#340
0%
#350
b110 7
b110 6
b10110 5
b10 B
b10 ?
1%
#360
0%
#370
b10111 5
b111 6
b111 7
b11 ?
b11 B
0"
1%
#380
0%
#390
b0 7
b1000 6
b11000 5
b100 B
b100 ?
1%
#400
0%
#410
1+
b11 9
b1 <
b0 -
b0 =
b0 A
b11001 5
01
b1001 6
10
b1 7
b101 ?
b101 B
1"
1%
#420
0%
#430
b10 7
b1010 6
b11010 5
b110 B
0"
b110 ?
1%
#440
0%
#450
b11011 5
b1011 6
b11 7
b111 ?
b111 B
1"
1%
#460
0%
#470
b100 7
b1100 6
b11100 5
b0 B
b0 ?
1%
#480
0%
#490
b11101 5
b1101 6
00
b101 7
b1 ?
b1 B
1%
#500
0%
#510
b110 7
b1110 6
b11110 5
b10 B
b10 ?
1%
#520
0%
#530
b11111 5
b1111 6
b111 7
b11 ?
b11 B
0"
1%
#540
0%
#550
b0 7
b0 6
b0 5
b100 B
b100 ?
1%
#560
0%
#570
b0 C
b11111111111111111111111111111111 )
b11111111111111111111111111111111 3
b11111111111111111111111111111111 8
b10 <
b0 9
1/
b1 5
11
b1 6
10
b1 7
b101 ?
b101 B
1"
1%
#580
0%
#590
b10 7
b10 6
b10 5
b110 B
0"
b110 ?
1%
#600
0%
#610
b11 5
b11 6
b11 7
b111 ?
b111 B
1%
#620
0%
#630
b100 7
b100 6
b100 5
b0 B
b0 ?
1%
#640
0%
0D
#650
b101 5
b101 6
00
b101 7
b1 ?
b1 B
1%
#660
0%
#670
b110 7
b110 6
b110 5
b10 B
b10 ?
1%
#680
0%
#690
b111 5
b111 6
b111 7
b11 ?
b11 B
1%
#700
0%
#710
b0 7
b1000 6
b1000 5
b100 B
b100 ?
1%
#720
0%
#730
b1 9
b11111111 .
b11111111 :
b11111111 >
b11 <
b1001 5
01
b1001 6
10
b1 7
b101 ?
b101 B
1%
#740
0%
#750
b10 7
b1010 6
b1010 5
b110 B
b110 ?
1%
#760
0%
#770
b1011 5
b1011 6
b11 7
b111 ?
b111 B
1%
#780
0%
#790
b100 7
b1100 6
b1100 5
b0 B
b0 ?
1%
#800
0%
#810
b1101 5
b1101 6
00
b101 7
b1 ?
b1 B
1%
#820
0%
#830
b110 7
b1110 6
b1110 5
b10 B
b10 ?
1%
#840
0%
#850
b1111 5
b1111 6
b111 7
b11 ?
b11 B
1%
#860
0%
#870
b0 7
b0 6
b10000 5
b100 B
b100 ?
1%
#880
0%
#890
b11111111 @
b11111111111111111111111111111111 (
b11111111111111111111111111111111 4
b11111111111111111111111111111111 ;
b0 <
b10 9
0/
b10001 5
11
b1 6
10
b1 7
b101 ?
b101 B
1%
#900
0%
#910
b10 7
b10 6
b10010 5
b110 B
b110 ?
1#
1%
#920
0%
#930
b10011 5
b11 6
b11 7
b111 ?
b111 B
1%
#940
0%
#950
b100 7
b100 6
b10100 5
b0 B
b0 ?
1%
#960
b11101110111011101110111011101110 $
b11101110111011101110111011101110 *
b11101110111011101110111011101110 2
b11101110111011101110111011101110 E
0%
1D
#970
b10101 5
b101 6
00
b101 7
b1 ?
b1 B
1%
#980
0%
#990
b110 7
b110 6
b10110 5
b10 B
b10 ?
1%
#1000
0%
#1010
b10111 5
b111 6
b111 7
b11 ?
b11 B
1%
#1020
0%
#1030
b0 7
b1000 6
b11000 5
b100 B
b100 ?
1%
#1040
0%
#1050
b11 9
b1 <
b11111111 -
b11111111 =
b11111111 A
b11001 5
01
b1001 6
10
b1 7
b101 ?
b101 B
1%
#1060
0%
#1070
b10 7
b1010 6
b11010 5
b110 B
b110 ?
1%
#1080
0%
#1090
b11011 5
b1011 6
b11 7
b111 ?
b111 B
1%
#1100
0%
#1110
b100 7
b1100 6
b11100 5
b0 B
b0 ?
1%
#1120
0%
#1130
b11101 5
b1101 6
00
b101 7
b1 ?
b1 B
1%
#1140
0%
#1150
b110 7
b1110 6
b11110 5
b10 B
b10 ?
1%
#1160
0%
#1170
b11111 5
b1111 6
b111 7
b11 ?
b11 B
1%
#1180
0%
#1190
b0 7
b0 6
b0 5
b100 B
b100 ?
1%
#1200
0%
#1210
b11111111 C
b11101110111011101110111011101110 )
b11101110111011101110111011101110 3
b11101110111011101110111011101110 8
b10 <
b0 9
1/
b1 5
11
b1 6
10
b1 7
b101 ?
b101 B
1%
#1220
0%
#1230
b10 7
b10 6
b10 5
b110 B
1"
b110 ?
1%
#1240
0%
#1250
b11 5
b11 6
b11 7
b111 ?
b111 B
1%
#1260
0%
#1270
b100 7
b100 6
b100 5
b0 B
b0 ?
1%
#1280
0%
0D
#1290
b101 5
b101 6
00
b101 7
b1 ?
b1 B
1%
#1300
0%
#1310
b110 7
b110 6
b110 5
b10 B
b10 ?
1%
#1320
0%
#1330
b111 5
b111 6
b111 7
b11 ?
b11 B
1%
#1340
0%
#1350
b0 7
b1000 6
b1000 5
b100 B
b100 ?
1%
#1360
0%
#1370
b1 9
b11101110 .
b11101110 :
b11101110 >
b11 <
b1001 5
01
b1001 6
10
b1 7
b101 ?
b101 B
1%
#1380
0%
#1390
b10 7
b1010 6
b1010 5
b110 B
b110 ?
1%
#1400
0%
#1410
b1011 5
b1011 6
b11 7
b111 ?
b111 B
1%
#1420
0%
#1430
b100 7
b1100 6
b1100 5
b0 B
b0 ?
1%
#1440
0%
#1450
b1101 5
b1101 6
00
b101 7
b1 ?
b1 B
1%
#1460
0%
#1470
b110 7
b1110 6
b1110 5
b10 B
b10 ?
1%
#1480
0%
#1490
b1111 5
b1111 6
b111 7
b11 ?
b11 B
1%
#1500
0%
#1510
b0 7
b0 6
b10000 5
b100 B
b100 ?
1%
#1520
0%
#1530
b11101110 @
b11101110111011101110111011101110 (
b11101110111011101110111011101110 4
b11101110111011101110111011101110 ;
b0 <
b10 9
0/
b10001 5
11
b1 6
10
b1 7
b101 ?
b101 B
1%
#1540
0%
#1550
b10 7
b10 6
b10010 5
b110 B
b110 ?
1%
#1560
0%
#1570
b10011 5
b11 6
b11 7
b111 ?
b111 B
1%
#1580
0%
#1590
b100 7
b100 6
b10100 5
b0 B
b0 ?
0#
1%
#1600
b11011101110111011101110111011101 $
b11011101110111011101110111011101 *
b11011101110111011101110111011101 2
b11011101110111011101110111011101 E
0%
1D
#1610
b10101 5
b101 6
00
b101 7
b1 ?
1#
b1 B
1%
#1620
0%
#1630
b110 7
b110 6
b10110 5
b10 B
b10 ?
1%
#1640
0%
#1650
b10111 5
b111 6
b111 7
b11 ?
b11 B
1%
#1660
0%
#1670
b0 7
b1000 6
b11000 5
b100 B
b100 ?
0#
1%
#1680
0%
#1690
b11 9
b1 <
b11101110 -
b11101110 =
b11101110 A
b11001 5
01
b1001 6
10
b1 7
b101 ?
1#
b101 B
1%
#1700
0%
#1710
b10 7
b1010 6
b11010 5
b110 B
b110 ?
1%
#1720
0%
#1730
b11011 5
b1011 6
b11 7
b111 ?
b111 B
1%
#1740
0%
#1750
b100 7
b1100 6
b11100 5
b0 B
b0 ?
0#
1%
#1760
0%
#1770
b11101 5
b1101 6
00
b101 7
b1 ?
1#
b1 B
1%
#1780
0%
#1790
b110 7
b1110 6
b11110 5
b10 B
b10 ?
1%
#1800
0%
#1810
b11111 5
b1111 6
b111 7
b11 ?
b11 B
1%
#1820
0%
#1830
b0 7
b0 6
b0 5
b100 B
b100 ?
0#
1%
#1840
0%
#1850
b11101110 C
b11011101110111011101110111011101 )
b11011101110111011101110111011101 3
b11011101110111011101110111011101 8
b10 <
b0 9
1/
b1 5
11
b1 6
10
b1 7
b101 ?
1#
b101 B
1%
#1860
0%
#1870
b10 7
b10 6
b10 5
b110 B
b110 ?
1%
#1880
0%
#1890
b11 5
b11 6
b11 7
b111 ?
b111 B
1%
#1900
0%
#1910
b100 7
b100 6
b100 5
b0 B
0"
b0 ?
0#
1%
#1920
0%
0D
#1930
b101 5
b101 6
00
b101 7
b1 ?
1#
b1 B
1"
1%
#1940
0%
#1950
b110 7
b110 6
b110 5
b10 B
b10 ?
1%
#1960
0%
#1970
b111 5
b111 6
b111 7
b11 ?
b11 B
1%
#1980
0%
#1990
b0 7
b1000 6
b1000 5
b100 B
0"
b100 ?
0#
1%
#2000
0%
#2010
b1 9
b11011101 .
b11011101 :
b11011101 >
b11 <
b1001 5
01
b1001 6
10
b1 7
b101 ?
1#
b101 B
1"
1%
#2020
0%
#2030
b10 7
b1010 6
b1010 5
b110 B
b110 ?
1%
#2040
0%
#2050
b1011 5
b1011 6
b11 7
b111 ?
b111 B
1%
#2060
0%
#2070
b100 7
b1100 6
b1100 5
b0 B
0"
b0 ?
0#
1%
#2080
0%
#2090
b1101 5
b1101 6
00
b101 7
b1 ?
1#
b1 B
1"
1%
#2100
0%
#2110
b110 7
b1110 6
b1110 5
b10 B
b10 ?
1%
#2120
0%
#2130
b1111 5
b1111 6
b111 7
b11 ?
b11 B
1%
#2140
0%
#2150
b0 7
b0 6
b10000 5
b100 B
0"
b100 ?
0#
1%
#2160
0%
#2170
b11011101 @
b11011101110111011101110111011101 (
b11011101110111011101110111011101 4
b11011101110111011101110111011101 ;
b0 <
b10 9
0/
b10001 5
11
b1 6
10
b1 7
b101 ?
1#
b101 B
1"
1%
#2180
0%
#2190
b10 7
b10 6
b10010 5
b110 B
b110 ?
1%
#2200
0%
#2210
b10011 5
b11 6
b11 7
b111 ?
0#
b111 B
1%
#2220
0%
#2230
b100 7
b100 6
b10100 5
b0 B
0"
b0 ?
1#
1%
#2240
b11001100110011001100110011001100 $
b11001100110011001100110011001100 *
b11001100110011001100110011001100 2
b11001100110011001100110011001100 E
0%
1D
#2250
b10101 5
b101 6
00
b101 7
b1 ?
b1 B
1"
1%
#2260
0%
#2270
b110 7
b110 6
b10110 5
b10 B
b10 ?
1%
#2280
0%
#2290
b10111 5
b111 6
b111 7
b11 ?
0#
b11 B
1%
#2300
0%
#2310
b0 7
b1000 6
b11000 5
b100 B
0"
b100 ?
1#
1%
#2320
0%
#2330
b11 9
b1 <
b11011101 -
b11011101 =
b11011101 A
b11001 5
01
b1001 6
10
b1 7
b101 ?
b101 B
1"
1%
#2340
0%
#2350
b10 7
b1010 6
b11010 5
b110 B
b110 ?
1%
#2360
0%
#2370
b11011 5
b1011 6
b11 7
b111 ?
0#
b111 B
1%
#2380
0%
#2390
b100 7
b1100 6
b11100 5
b0 B
0"
b0 ?
1#
1%
#2400
0%
#2410
b11101 5
b1101 6
00
b101 7
b1 ?
b1 B
1"
1%
#2420
0%
#2430
b110 7
b1110 6
b11110 5
b10 B
b10 ?
1%
#2440
0%
#2450
b11111 5
b1111 6
b111 7
b11 ?
0#
b11 B
1%
#2460
0%
#2470
b0 7
b0 6
b0 5
b100 B
0"
b100 ?
1#
1%
#2480
0%
#2490
b11011101 C
b11001100110011001100110011001100 )
b11001100110011001100110011001100 3
b11001100110011001100110011001100 8
b10 <
b0 9
1/
b1 5
11
b1 6
10
b1 7
b101 ?
b101 B
1"
1%
#2500
0%
#2510
b10 7
b10 6
b10 5
b110 B
b110 ?
1%
#2520
0%
#2530
b11 5
b11 6
b11 7
b111 ?
0#
b111 B
0"
1%
#2540
0%
#2550
b100 7
b100 6
b100 5
b0 B
1"
b0 ?
1#
1%
#2560
0%
0D
#2570
b101 5
b101 6
00
b101 7
b1 ?
b1 B
1%
#2580
0%
#2590
b110 7
b110 6
b110 5
b10 B
b10 ?
1%
#2600
0%
#2610
b111 5
b111 6
b111 7
b11 ?
0#
b11 B
0"
1%
#2620
0%
#2630
b0 7
b1000 6
b1000 5
b100 B
1"
b100 ?
1#
1%
#2640
0%
#2650
b1 9
b11001100 .
b11001100 :
b11001100 >
b11 <
b1001 5
01
b1001 6
10
b1 7
b101 ?
b101 B
1%
#2660
0%
#2670
b10 7
b1010 6
b1010 5
b110 B
b110 ?
1%
#2680
0%
#2690
b1011 5
b1011 6
b11 7
b111 ?
0#
b111 B
0"
1%
#2700
0%
#2710
b100 7
b1100 6
b1100 5
b0 B
1"
b0 ?
1#
1%
#2720
0%
#2730
b1101 5
b1101 6
00
b101 7
b1 ?
b1 B
1%
#2740
0%
#2750
b110 7
b1110 6
b1110 5
b10 B
b10 ?
1%
#2760
0%
#2770
b1111 5
b1111 6
b111 7
b11 ?
0#
b11 B
0"
1%
#2780
0%
#2790
b0 7
b0 6
b10000 5
b100 B
1"
b100 ?
1#
1%
#2800
0%
#2810
b11001100 @
b11001100110011001100110011001100 (
b11001100110011001100110011001100 4
b11001100110011001100110011001100 ;
b0 <
b10 9
0/
b10001 5
11
b1 6
10
b1 7
b101 ?
b101 B
1%
#2820
0%
#2830
b10 7
b10 6
b10010 5
b110 B
b110 ?
1%
#2840
0%
#2850
b10011 5
b11 6
b11 7
b111 ?
0#
b111 B
0"
1%
#2860
0%
#2870
b100 7
b100 6
b10100 5
b0 B
1"
b0 ?
1%
#2880
b10111011101110111011101110111011 $
b10111011101110111011101110111011 *
b10111011101110111011101110111011 2
b10111011101110111011101110111011 E
0!
0%
1D
#2890
b10101 5
b101 6
00
b101 7
b1 ?
1#
b1 B
1%
#2900
0%
#2910
b110 7
b110 6
b10110 5
b10 B
b10 ?
1%
#2920
0%
#2930
b10111 5
b111 6
b111 7
b11 ?
0#
b11 B
0"
1%
#2940
0%
#2950
b0 7
b1000 6
b11000 5
b100 B
1"
b100 ?
1%
#2960
0%
#2970
b11 9
b1 <
b11001100 -
b11001100 =
b11001100 A
b11001 5
01
b1001 6
10
b1 7
b101 ?
1#
b101 B
1%
#2980
0%
#2990
b10 7
b1010 6
b11010 5
b110 B
b110 ?
1%
#3000
0%
#3010
b11011 5
b1011 6
b11 7
b111 ?
0#
b111 B
0"
1%
#3020
0%
#3030
b100 7
b1100 6
b11100 5
b0 B
1"
b0 ?
1%
#3040
0%
#3050
b11101 5
b1101 6
00
b101 7
b1 ?
1#
b1 B
1%
#3060
0%
#3070
b110 7
b1110 6
b11110 5
b10 B
b10 ?
1%
#3080
0%
#3090
b11111 5
b1111 6
b111 7
b11 ?
0#
b11 B
0"
1%
#3100
0%
#3110
b0 7
b0 6
b0 5
b100 B
1"
b100 ?
1%
#3120
0%
#3130
b0 )
b0 3
b0 8
0'
b11001100 C
b10 <
b0 9
1/
b1 5
11
b1 6
10
b1 7
b101 ?
1#
b101 B
1%
#3140
0%
#3150
b10 7
b10 6
b10 5
b110 B
b110 ?
1%
#3160
0%
#3170
b11 5
b11 6
b11 7
b111 ?
0#
b111 B
0"
1%
#3180
0%
#3190
b100 7
b100 6
b100 5
b0 B
b0 ?
1%
#3200
0%
0D
#3210
b101 5
b101 6
00
b101 7
b1 ?
1#
b1 B
1"
1%
#3220
0%
#3230
b110 7
b110 6
b110 5
b10 B
b10 ?
1%
#3240
0%
#3250
b111 5
b111 6
b111 7
b11 ?
0#
b11 B
0"
1%
#3260
0%
#3270
b0 7
b1000 6
b1000 5
b100 B
b100 ?
1%
#3280
0%
#3290
0,
b11 <
b1001 5
01
b1001 6
10
b1 7
b101 ?
1#
b101 B
1"
1%
#3300
0%
#3310
b10 7
b1010 6
b1010 5
b110 B
b110 ?
1%
#3320
0%
#3330
b1011 5
b1011 6
b11 7
b111 ?
0#
b111 B
0"
1%
#3340
0%
#3350
b100 7
b1100 6
b1100 5
b0 B
b0 ?
1%
#3360
0%
#3370
b1101 5
b1101 6
00
b101 7
b1 ?
1#
b1 B
1"
1%
#3380
0%
#3390
b110 7
b1110 6
b1110 5
b10 B
b10 ?
1%
#3400
0%
#3410
b1111 5
b1111 6
b111 7
b11 ?
0#
b11 B
0"
1%
#3420
0%
#3430
b0 7
b0 6
b10000 5
b100 B
b100 ?
1%
#3440
0%
#3450
b0 (
b0 4
b0 ;
0&
b10111100 @
b0 <
0/
b10001 5
11
b1 6
10
b1 7
b101 ?
1#
b101 B
1"
1%
#3460
0%
#3470
b10 7
b10 6
b10010 5
b110 B
b110 ?
0#
1%
#3480
0%
#3490
b10011 5
b11 6
b11 7
b111 ?
1#
b111 B
0"
1%
#3500
0%
#3510
b100 7
b100 6
b10100 5
b0 B
b0 ?
1%
#3520
b10101010101010101010101010101010 $
b10101010101010101010101010101010 *
b10101010101010101010101010101010 2
b10101010101010101010101010101010 E
0%
1D
#3530
b10101 5
b101 6
00
b101 7
b1 ?
b1 B
1"
1%
#3540
0%
#3550
b110 7
b110 6
b10110 5
b10 B
b10 ?
1%
#3560
0%
#3570
b10111 5
b111 6
b111 7
b11 ?
0#
b11 B
0"
1%
#3580
0%
#3590
b0 7
b1000 6
b11000 5
b100 B
b100 ?
1%
#3600
0%
#3610
0+
b11001 5
01
b1001 6
10
b1 7
b101 ?
1#
b101 B
1"
1%
#3620
0%
#3630
b10 7
b1010 6
b11010 5
b110 B
b110 ?
0#
1%
