phy/probador_phy.v
// Fecha: 21-10-2021
// Probador del transmisor phy_tx
// Version 1.0

module probador_phy(
    output reg clk_32f,
    output reg [31:0] data_in,
    output reg valid_in,
    input [31:0] data_out,
    input valid_out);

	initial clk_32f <= 0;
    reg clk = 0 ;
	always #1 clk_32f <= ~clk_32f;
    always #32 clk <= ~clk;

	initial begin
	$dumpfile("phy.vcd");
	$dumpvars;

	
	{data_in} <= 32'h00000000;
    {valid_in} <= 1;

    @(posedge clk_32f);
    @(posedge clk_32f);
    @(posedge clk_32f);
    @(posedge clk_32f);
    @(posedge clk_32f);
    @(posedge clk_32f);
    @(posedge clk_32f);
    @(posedge clk_32f);
    @(posedge clk_32f);
    @(posedge clk_32f);
    @(posedge clk_32f);
    @(posedge clk_32f);
    @(posedge clk_32f);
    @(posedge clk_32f);
    @(posedge clk_32f);
    @(posedge clk_32f);
    @(posedge clk_32f);
    @(posedge clk_32f);
    @(posedge clk_32f);
    @(posedge clk_32f);
    @(posedge clk_32f);
    @(posedge clk_32f);
    @(posedge clk_32f);
    @(posedge clk_32f);
    @(posedge clk_32f);
    @(posedge clk_32f);
    @(posedge clk_32f);
    @(posedge clk_32f);


	@(posedge clk_32f);

    {valid_in} <= 1;
	data_in <= 32'hFFFFFFFF;
    @(posedge clk_32f);
    @(posedge clk_32f);
    @(posedge clk_32f);
    @(posedge clk_32f);
    @(posedge clk_32f);
    @(posedge clk_32f);
    @(posedge clk_32f);
    @(posedge clk_32f);
    @(posedge clk_32f);
    @(posedge clk_32f);
    @(posedge clk_32f);
    @(posedge clk_32f);
    @(posedge clk_32f);
    @(posedge clk_32f);
    @(posedge clk_32f);
    @(posedge clk_32f);

    data_in <= 32'hEEEEEEEE;
    @(posedge clk_32f);
    @(posedge clk_32f);
    @(posedge clk_32f);
    @(posedge clk_32f);
    @(posedge clk_32f);
    @(posedge clk_32f);
    @(posedge clk_32f);
    @(posedge clk_32f);
    @(posedge clk_32f);
    @(posedge clk_32f);
    @(posedge clk_32f);
    @(posedge clk_32f);
    @(posedge clk_32f);
    @(posedge clk_32f);
    @(posedge clk_32f);
    @(posedge clk_32f);
  
    data_in <= 32'hDDDDDDDD;

    @(posedge clk_32f);
	@(posedge clk_32f);
    @(posedge clk_32f);
    @(posedge clk_32f);
    @(posedge clk_32f);
    @(posedge clk_32f);
    @(posedge clk_32f);
    @(posedge clk_32f);
    @(posedge clk_32f);
    @(posedge clk_32f);
    @(posedge clk_32f);
    @(posedge clk_32f);
    @(posedge clk_32f);
    @(posedge clk_32f);
    @(posedge clk_32f);
    @(posedge clk_32f);

	
    valid_in <=1;
    data_in <= 32'hCCCCCCCC;
    @(posedge clk_32f);
    @(posedge clk_32f);
    @(posedge clk_32f);
    @(posedge clk_32f);
    @(posedge clk_32f);
    @(posedge clk_32f);
    @(posedge clk_32f);
    @(posedge clk_32f);
    @(posedge clk_32f);
    @(posedge clk_32f);
    @(posedge clk_32f);
    @(posedge clk_32f);
    @(posedge clk_32f);
    @(posedge clk_32f);
    @(posedge clk_32f);
    @(posedge clk_32f);

    valid_in <=0;
    data_in <= 32'hBBBBBBBB;

    @(posedge clk_32f);
    @(posedge clk_32f);
    @(posedge clk_32f);
    @(posedge clk_32f);
    @(posedge clk_32f);
    @(posedge clk_32f);
    @(posedge clk_32f);
    @(posedge clk_32f);
    @(posedge clk_32f);
    @(posedge clk_32f);
    @(posedge clk_32f);
    @(posedge clk_32f);
    @(posedge clk_32f);
    @(posedge clk_32f);
    @(posedge clk_32f);
    @(posedge clk_32f);

	valid_in <=0;
    data_in <= 32'hAAAAAAAA;
 
	#15 $finish;
	end


endmodule

phy/byte_unstriping.v
module byte_unstriping(
    input clk_f,
    input clk_2f,
    input valid_0,
    input valid_1,
    input [31:0] lane_0,
    input [31:0] lane_1,
    output reg [31:0] data_out,
    output reg valid_out
    
);
initial begin
    data_out=32'h00000000;
    valid_out <= 1'b0;


end
    always @(posedge clk_2f ) 
        begin
            if (valid_0 == 0) 
                begin
                    valid_out <= 1'b0;
                    data_out <= 32'h00000000;
                    
                end 
            else 
                begin
                    valid_out <= 1'b1;
                    data_out = lane_0;

                    
                end
            
        end
    always @(negedge clk_2f ) 
        begin
            if (valid_1 == 0) 
                begin
                    valid_out <= 1'b0;
                    data_out <= 32'h00000000;
                    
                end 
            else 
                begin
                    valid_out <= 1'b1;
                    data_out = lane_1;

                    
                end
            
        end
    


endmodule

phy/conv_8_32.v
//Fecha: 04-10-2021
//Convertidor de 8 bits a 32 bits
//Version 1.0 

module conv_8_32 (input clk_4f, //senal de reloj
    input valid_0, //bit de entrada de validez
    input [7:0] data_in, //entrada de 32 bits
    output reg [31:0] data_out,//salida de 8 bits
    output reg valid_out); //bit de salida de validez

    reg [1:0] contador = 2'b00;//contador

    always @(posedge clk_4f) begin
    if (valid_0 == 1) begin
      case (contador)
        2'b00: data_out[31:24] = data_in;
        2'b01: data_out[23:16] = data_in;
        2'b10: data_out[15:8] = data_in;
        2'b11: data_out[7:0] = data_in;
        default: data_out = 8'h00;
      endcase
      contador <= contador + 1;
      valid_out <= valid_0;
      end
    else begin
        valid_out <= valid_0;
        contador = 2'b00;
    end
    end

endmodule

phy/serial_paralelo.v
 /* ***********************************************************
                    Universidad de Costa Rica
                 Escuela de Ingenieria Electrica
                            IE-0323
                      Circuitos Digitales 1

                        serial_paralelo.v

Descripcion:
  

*********************************************************** */

module serial_paralelo(
	//ENTRADAS
			
			input data_in,			//entrada de datos
			input clk_32f,			//clock frecuencia 32
			input clk_4f,			//clock frecuencia 4
	//SALIDAS
	
			output reg	[7:0] data_out, 	//salida de datos	
			output reg  valid_out			//valid
						
);
			reg [7:0] buffer = 0;					//guarda datos actuales (n)
			reg [7:0] buffer_pasado;		//guarda datos pasados (n-1)
			reg active =1'b0; //active
			integer contador = 0;					//
			reg [2:0] contador2 = 3'b000;	
			integer contador_BC = 0;				//contador de datos BC entrada*se buscan 4
	initial begin
	data_out <= 8'b00000000;
	valid_out <= 1'b0;
	end


	always @(posedge clk_32f) begin

		 case (contador2)
            3'b101: buffer[7] <= data_in;
            3'b110: buffer[6] <= data_in;
            3'b111: buffer[5] <= data_in;
            3'b000: buffer[4] <= data_in;
            3'b001: buffer[3] <= data_in;
            3'b010: buffer[2] <= data_in;
            3'b011: buffer[1] <= data_in;
            3'b100: buffer[0] <= data_in;
            default: buffer <= 0;
        endcase
    
    contador2 = contador2 + 1;                // Aumentar el contador
		
	end
	
	always @(posedge clk_32f)
	
	begin
				
				if (contador_BC == 4 && contador == 1)
				begin
					
					active <= 1;
					
					if (buffer != 8'hBC)
					
					begin
						
						valid_out	<= 1;
						data_out <= buffer;
					end
					
				else if (buffer_pasado != 8'hBC && buffer == 8'hBC)
					
					begin
						
						valid_out	<= 0;
						contador_BC <= 0;
						data_out <= 0;//modificacion
						
					end
			end
				
				if (contador_BC < 4 && buffer == 8'hBC)
				
				begin
					
						valid_out	<= 0;
						data_out <= 0;
						contador_BC <= contador_BC + 1;
				end
					
				if (contador == 1)
				begin
						buffer_pasado <=buffer;
				end
				
				if (contador == 7)
				begin
						contador <= 0;
				end
				
				else if (contador != 7)
				begin
						contador <= contador + 1;
				end
		
	end
endmodule

phy/clock_generator.v
module clock_generator(
    input clk_32f,
    output reg clk_f,
    output reg clk_2f,
    output reg clk_4f
    );

    initial clk_f <= 0;
    initial clk_2f <= 0;
    initial clk_4f <= 0;
    
    reg [27:0] counter1 = 28'd4;
    reg [27:0] counter2 = 28'd4;
    reg [27:0] counter3 = 28'd4;
    parameter df_1 = 28'd32; //divisor de frecuencia
    parameter df_2 = 28'd16; //divisor de frecuencia
    parameter df_4 = 28'd8; //divisor de frecuencia

    always @(posedge clk_32f)
    begin
      counter1<= counter1 + 28'd1;
        if (counter1 >=(df_1-1))
            counter1 <= 28'd0;
            clk_f <= (counter1 <df_1/2)?1'b1:1'b0;
    end

    always @(posedge clk_32f)
    begin
      counter2 <= counter2 + 28'd1;
        if (counter2 >=(df_2-1))
            counter2 <= 28'd0;
            clk_2f <= (counter2 <df_2/2)?1'b1:1'b0;
    end
    
    always @(posedge clk_32f)
    begin
      counter3 <= counter3 + 28'd1;
        if (counter3 >=(df_4-1))
            counter3 <= 28'd0;
            clk_4f <= (counter3 <df_4/2)?1'b1:1'b0;
    end

    
endmodule

phy/phy_rx.v
// Fecha: 21-10-2021
// Modulo del receptor phy_rx
// Version 1.0

`include "byte_unstriping.v"
`include "conv_8_32.v"
`include "serial_paralelo.v"


module phy_rx (input phy_tx_out_0,
    input phy_tx_out_1,
    input clk_32f,
    output [31:0] data_out,
    output valid_out);

    //Cables para salidas de modulo de clock_generator
    wire clk_2f, clk_4f, clk_32f;

    //Cables para salidas de modulos de serial_paralelo
    wire valid_0, valid_1;
    wire [7:0] paralelo_0;
    wire [7:0] paralelo_1;

    //Cables para salidas de modulos de conv_8_32
    wire conv_8_32_valid_0, conv_8_32_valid_1;
    wire [31:0] lane_0;
    wire [31:0] lane_1;

    clock_generator clock_generator(/*AUTOINST*/
				    // Outputs
				    .clk_f		(clk_f),
				    .clk_2f		(clk_2f),
				    .clk_4f		(clk_4f),
				    // Inputs
				    .clk_32f		(clk_32f));

    serial_paralelo sign_0(/*AUTOINST*/
			   // Outputs
			   .data_out		(paralelo_0),
			   .valid_out		(valid_0),
			   // Inputs
			   .data_in		(phy_tx_out_0),
			   .clk_32f		(clk_32f),
			   .clk_4f		(clk_4f));

    serial_paralelo sign_1(/*AUTOINST*/
			   // Outputs
			   .data_out		(paralelo_1),
			   .valid_out		(valid_1),
			   // Inputs
			   .data_in		(phy_tx_out_1),
			   .clk_32f		(clk_32f),
			   .clk_4f		(clk_4f));

    conv_8_32 conv_0(/*AUTOINST*/
		     // Outputs
		     .data_out		(lane_0),
		     .valid_out		(conv_8_32_valid_0),
		     // Inputs
		     .clk_4f		(clk_4f),
		     .valid_0		(valid_0),
		     .data_in		(paralelo_0));

    conv_8_32 conv_1(/*AUTOINST*/
		     // Outputs
		     .data_out		(lane_1),
		     .valid_out		(conv_8_32_valid_1),
		     // Inputs
		     .clk_4f		(clk_4f),
		     .valid_0		(valid_1),
		     .data_in		(paralelo_1));

    byte_unstriping byte_unstriping(/*AUTOINST*/
				    // Outputs
				    .data_out		(data_out),
				    .valid_out		(valid_out),
				    // Inputs
				    .clk_f		(clk_f),
				    .clk_2f		(clk_2f),
				    .valid_0		(conv_8_32_valid_0),
				    .valid_1		(conv_8_32_valid_1),
				    .lane_0		(lane_0),
				    .lane_1		(lane_1));

    endmodule

phy/paralelo_serial.v
// Fecha: 20-10-2021
// Convertidor señal serial-paralelo
// Version 1.0

// Módulo con la lógica del convertidor de señales
module paralelo_serial (
    input clk_4f,
    input clk_32f,
    input valid_in,
    input [7:0] data_in,
    output reg data_out
);

    initial begin
      data_out <= 1'b0;
    end
    
    reg [7:0] data2send;            // Cable para almacenar la señal para la salida en 8 bits
    reg [2:0] contador = 3'b000;    // Contador para sincronizar salida data_out

    always @(posedge clk_4f) begin
    if (valid_in == 1) begin
        data2send <= data_in;        // Asignar data_in a data2out
    end

    if (valid_in == 0) begin
        data2send <= 8'hBC;         // En caso de que valid sea 0 se le asigna hex(BC)
    end

    end  

    

    always @(posedge clk_32f) begin         // Logica para convertir señal paralelo a serial
        case (contador)
            3'b101: data_out = data2send[7];
            3'b110: data_out = data2send[6];
            3'b111: data_out = data2send[5];
            3'b000: data_out = data2send[4];
            3'b001: data_out = data2send[3];
            3'b010: data_out = data2send[2];
            3'b011: data_out = data2send[1];
            3'b100: data_out = data2send[0];
            default: data_out = 1'b0;
        endcase
    
    contador = contador + 1;                // Aumentar el contador
    end


endmodule

phy/conv_32_8.v
//Fecha: 04-10-2021
//Convertidor de 32 bits a 8 bits
//Version 1.0 

module conv_32_8 (input clk_4f, //senal de reloj
    input valid_in, //bit de entrada de validez
    input [31:0] data_in, //entrada de 32 bits
    output reg [7:0] data_out,//salida de 8 bits
    output reg valid_out); //bit de salida de validez

    reg [1:0] contador = 2'b00;//contador
    initial valid_out <= 0;

    always @(posedge clk_4f) begin
    if (data_in == 0) begin
        valid_out <= 0;
    end

    else begin
      if (valid_in == 1) begin
      case (contador)
        2'b00: data_out = data_in[31:24];
        2'b01: data_out = data_in[23:16];
        2'b10: data_out = data_in[15:8];
        2'b11: data_out = data_in[7:0];
        default: data_out = 8'h00;
      endcase
      contador = contador + 1;
      valid_out <= valid_in;
      end
    else begin
        valid_out <= 1'b0;
        contador = 2'b00;
    end

    end

    
    end

endmodule

phy/byte_striping.v
module byte_striping(
    input clk_2f,
    input [31:0] data_in,
    input valid_in,
    output reg [31:0] lane_0,
    output reg [31:0] lane_1,
    output reg valid_0,
    output reg valid_1
);

    reg counter = 0;
initial begin
    lane_0<=32'h00000000;
    lane_1<=32'h00000000;
    valid_0 <= 1'b1;
    valid_1 <= 1'b1;

end
    always @(posedge clk_2f ) begin
        if (counter==0) 
            begin
            if (valid_in ==0) 
                begin
                    valid_0 <= 1'b0;
                    lane_0 <= 32'h00000000;
                    
                end 
            else 
                begin
                    valid_0 <= 1'b1;
                    lane_0 <= data_in;
       
                end
        
            end 
            
        else begin
                if (valid_in ==0) 
                begin
                    valid_1 <= 1'b0;
                    lane_1 <= 32'h00000000;   
                end 
                else 
                begin
                    valid_1 <= 1'b1;
                    lane_1 <= data_in;    
                end
            
            end
        counter = ~counter;
    end
        

endmodule

phy/phy_tx.v
// Fecha: 21-10-2021
// Modulo del transmisor phy_tx
// Version 1.0

`include "byte_striping.v"
`include "conv_32_8.v"
`include "paralelo_serial.v"


module phy_tx (input [31:0] data_in,
    input valid_in,
    input clk_32f,
    output phy_tx_out_0,
    output phy_tx_out_1);

    //Cables para salidas de modulo de clock_generator
    wire clk_2f, clk_4f, clk_32f;

    //Cables para salidas de modulo de byte_striping
    wire valid_0, valid_1;
    wire [31:0] lane_0;
    wire [31:0] lane_1;

    //Cables para salidas de modulos de conv_32_8
    wire [7:0] conv_32_8_out_0;
    wire conv_32_8_valid_0, conv_32_8_valid_1;
    wire [7:0] conv_32_8_out_1;

    clock_generator clock_generator(/*AUTOINST*/
				    // Outputs
				    .clk_f		(clk_f),
				    .clk_2f		(clk_2f),
				    .clk_4f		(clk_4f),
				    // Inputs
				    .clk_32f		(clk_32f));

    byte_striping byte_striping(/*AUTOINST*/
				// Outputs
				.lane_0		(lane_0[31:0]),
				.lane_1		(lane_1[31:0]),
				.valid_0	(valid_0),
				.valid_1	(valid_1),
				// Inputs
				.clk_2f		(clk_2f),
				.data_in	(data_in[31:0]),
				.valid_in	(valid_in));

    conv_32_8 conv_0(/*AUTOINST*/
		     // Outputs
		     .data_out		(conv_32_8_out_0),
		     .valid_out		(conv_32_8_valid_0),
		     // Inputs
		     .clk_4f		(clk_4f),
		     .valid_in		(valid_0),
		     .data_in		(lane_0));

    conv_32_8 conv_1(/*AUTOINST*/
		     // Outputs
		     .data_out		(conv_32_8_out_1),
		     .valid_out		(conv_32_8_valid_1),
		     // Inputs
		     .clk_4f		(clk_4f),
		     .valid_in		(valid_1),
		     .data_in		(lane_1));

    paralelo_serial sign_0(/*AUTOINST*/
			   // Outputs
			   .data_out		(phy_tx_out_0),
			   // Inputs
			   .clk_4f		(clk_4f),
			   .clk_32f		(clk_32f),
			   .valid_in		(conv_32_8_valid_0),
			   .data_in		(conv_32_8_out_0));

    paralelo_serial sign_1(/*AUTOINST*/
			   // Outputs
			   .data_out		(phy_tx_out_1),
			   // Inputs
			   .clk_4f		(clk_4f),
			   .clk_32f		(clk_32f),
			   .valid_in		(conv_32_8_valid_1),
			   .data_in		(conv_32_8_out_1));

    endmodule

phy/phy.v
// Fecha: 21-10-2021
// Modulo del receptor phy_rx
// Version 1.0
`include "phy_rx.v"
`include "phy_tx.v"
`include "clock_generator.v"


module phy (input [31:0] data_in,
    input valid_in,
    input clk_32f,
    output [31:0] data_out,
    output valid_out);

    //Cables para salidas de modulo de phy_tx
    wire phy_tx_out_0, phy_tx_out_1;

    phy_tx phy_tx(/*AUTOINST*/
		  // Outputs
		  .phy_tx_out_0		(phy_tx_out_0),
		  .phy_tx_out_1		(phy_tx_out_1),
		  // Inputs
		  .data_in		(data_in[31:0]),
		  .valid_in		(valid_in),
		  .clk_32f		(clk_32f));

    phy_rx phy_rx(/*AUTOINST*/
		  // Outputs
		  .data_out		(data_out[31:0]),
		  .valid_out		(valid_out),
		  // Inputs
		  .phy_tx_out_0		(phy_tx_out_0),
		  .phy_tx_out_1		(phy_tx_out_1),
		  .clk_32f		(clk_32f));

    endmodule

phy/banco_phy.v
//Fecha: 21-10-2021
//Version 1.0

`timescale 	1ns	/ 100ps
// escala	unidad temporal (valor de "#1") / precisión

// includes de archivos de verilog
`include "phy.v"
//`include "yosys_phy.v"
`include "probador_phy.v"

module banco_phy_tx; // Testbench

    //Inputs
    wire clk_32f, valid_in;
    wire [31:0] data_in;

    //Outputs
	wire valid_out;
    wire [31:0] data_out;

	// Se instancian los modulos


	phy conductual(/*AUTOINST*/
		       // Outputs
		       .data_out	(data_out[31:0]),
		       .valid_out	(valid_out),
		       // Inputs
		       .data_in		(data_in[31:0]),
		       .valid_in	(valid_in),
		       .clk_32f		(clk_32f));


	/*yosys_phy estructural();*/


	// Probador: generador de señales y monitor
	probador_phy probador_phy(/*AUTOINST*/
				  // Outputs
				  .clk_32f		(clk_32f),
				  .data_in		(data_in[31:0]),
				  .valid_in		(valid_in),
				  // Inputs
				  .data_out		(data_out),
				  .valid_out		(valid_out));

endmodule

Avance 2/phy.vcd
$date
	Fri Oct 22 22:37:17 2021
$end
$version
	Icarus Verilog
$end
$timescale
	100ps
$end
$scope module banco_phy_tx $end
$var wire 1 ! valid_out $end
$var wire 1 " valid_in $end
$var wire 32 # data_out [31:0] $end
$var wire 32 $ data_in [31:0] $end
$var wire 1 % clk_32f $end
$scope module conductual $end
$var wire 1 ! valid_out $end
$var wire 1 " valid_in $end
$var wire 1 & phy_tx_out_1 $end
$var wire 1 ' phy_tx_out_0 $end
$var wire 32 ( data_out [31:0] $end
$var wire 32 ) data_in [31:0] $end
$var wire 1 % clk_32f $end
$scope module phy_rx $end
$var wire 1 ! valid_out $end
$var wire 1 * valid_1 $end
$var wire 1 + valid_0 $end
$var wire 1 & phy_tx_out_1 $end
$var wire 1 ' phy_tx_out_0 $end
$var wire 8 , paralelo_1 [7:0] $end
$var wire 8 - paralelo_0 [7:0] $end
$var wire 32 . lane_1 [31:0] $end
$var wire 32 / lane_0 [31:0] $end
$var wire 32 0 data_out [31:0] $end
$var wire 1 1 conv_8_32_valid_1 $end
$var wire 1 2 conv_8_32_valid_0 $end
$var wire 1 3 clk_f $end
$var wire 1 4 clk_4f $end
$var wire 1 % clk_32f $end
$var wire 1 5 clk_2f $end
$scope module byte_unstriping $end
$var wire 1 1 valid_1 $end
$var wire 1 2 valid_0 $end
$var wire 32 6 lane_1 [31:0] $end
$var wire 32 7 lane_0 [31:0] $end
$var wire 1 3 clk_f $end
$var wire 1 5 clk_2f $end
$var reg 32 8 data_out [31:0] $end
$var reg 1 ! valid_out $end
$upscope $end
$scope module clock_generator $end
$var wire 1 % clk_32f $end
$var reg 1 5 clk_2f $end
$var reg 1 4 clk_4f $end
$var reg 1 3 clk_f $end
$var reg 28 9 counter1 [27:0] $end
$var reg 28 : counter2 [27:0] $end
$var reg 28 ; counter3 [27:0] $end
$upscope $end
$scope module conv_0 $end
$var wire 1 4 clk_4f $end
$var wire 1 + valid_0 $end
$var wire 8 < data_in [7:0] $end
$var reg 2 = contador [1:0] $end
$var reg 32 > data_out [31:0] $end
$var reg 1 2 valid_out $end
$upscope $end
$scope module conv_1 $end
$var wire 1 4 clk_4f $end
$var wire 1 * valid_0 $end
$var wire 8 ? data_in [7:0] $end
$var reg 2 @ contador [1:0] $end
$var reg 32 A data_out [31:0] $end
$var reg 1 1 valid_out $end
$upscope $end
$scope module sign_0 $end
$var wire 1 4 clk_4f $end
$var wire 1 ' data_in $end
$var wire 1 % clk_32f $end
$var reg 1 B active $end
$var reg 8 C buffer [7:0] $end
$var reg 8 D buffer_pasado [7:0] $end
$var reg 3 E contador2 [2:0] $end
$var reg 8 F data_out [7:0] $end
$var reg 1 + valid_out $end
$var integer 32 G contador [31:0] $end
$var integer 32 H contador_BC [31:0] $end
$upscope $end
$scope module sign_1 $end
$var wire 1 4 clk_4f $end
$var wire 1 & data_in $end
$var wire 1 % clk_32f $end
$var reg 1 I active $end
$var reg 8 J buffer [7:0] $end
$var reg 8 K buffer_pasado [7:0] $end
$var reg 3 L contador2 [2:0] $end
$var reg 8 M data_out [7:0] $end
$var reg 1 * valid_out $end
$var integer 32 N contador [31:0] $end
$var integer 32 O contador_BC [31:0] $end
$upscope $end
$upscope $end
$scope module phy_tx $end
$var wire 1 " valid_in $end
$var wire 1 P valid_1 $end
$var wire 1 Q valid_0 $end
$var wire 1 & phy_tx_out_1 $end
$var wire 1 ' phy_tx_out_0 $end
$var wire 32 R lane_1 [31:0] $end
$var wire 32 S lane_0 [31:0] $end
$var wire 32 T data_in [31:0] $end
$var wire 1 U conv_32_8_valid_1 $end
$var wire 1 V conv_32_8_valid_0 $end
$var wire 8 W conv_32_8_out_1 [7:0] $end
$var wire 8 X conv_32_8_out_0 [7:0] $end
$var wire 1 Y clk_f $end
$var wire 1 Z clk_4f $end
$var wire 1 % clk_32f $end
$var wire 1 [ clk_2f $end
$scope module byte_striping $end
$var wire 1 " valid_in $end
$var wire 32 \ data_in [31:0] $end
$var wire 1 [ clk_2f $end
$var reg 1 ] counter $end
$var reg 32 ^ lane_0 [31:0] $end
$var reg 32 _ lane_1 [31:0] $end
$var reg 1 Q valid_0 $end
$var reg 1 P valid_1 $end
$upscope $end
$scope module clock_generator $end
$var wire 1 % clk_32f $end
$var reg 1 [ clk_2f $end
$var reg 1 Z clk_4f $end
$var reg 1 Y clk_f $end
$var reg 28 ` counter1 [27:0] $end
$var reg 28 a counter2 [27:0] $end
$var reg 28 b counter3 [27:0] $end
$upscope $end
$scope module conv_0 $end
$var wire 1 Z clk_4f $end
$var wire 32 c data_in [31:0] $end
$var wire 1 Q valid_in $end
$var reg 2 d contador [1:0] $end
$var reg 8 e data_out [7:0] $end
$var reg 1 V valid_out $end
$upscope $end
$scope module conv_1 $end
$var wire 1 Z clk_4f $end
$var wire 32 f data_in [31:0] $end
$var wire 1 P valid_in $end
$var reg 2 g contador [1:0] $end
$var reg 8 h data_out [7:0] $end
$var reg 1 U valid_out $end
$upscope $end
$scope module sign_0 $end
$var wire 1 Z clk_4f $end
$var wire 8 i data_in [7:0] $end
$var wire 1 V valid_in $end
$var wire 1 % clk_32f $end
$var reg 3 j contador [2:0] $end
$var reg 8 k data2send [7:0] $end
$var reg 1 ' data_out $end
$upscope $end
$scope module sign_1 $end
$var wire 1 Z clk_4f $end
$var wire 8 l data_in [7:0] $end
$var wire 1 U valid_in $end
$var wire 1 % clk_32f $end
$var reg 3 m contador [2:0] $end
$var reg 8 n data2send [7:0] $end
$var reg 1 & data_out $end
$upscope $end
$upscope $end
$upscope $end
$scope module probador_phy $end
$var wire 32 o data_out [31:0] $end
$var wire 1 ! valid_out $end
$var reg 1 p clk $end
$var reg 1 % clk_32f $end
$var reg 32 q data_in [31:0] $end
$var reg 1 " valid_in $end
$upscope $end
$upscope $end
$enddefinitions $end
#0
$dumpvars
b0 q
0p
bx o
bx n
b0 m
bx l
bx k
b0 j
bx i
bx h
b0 g
b0 f
bx e
b0 d
b0 c
b100 b
b100 a
b100 `
b0 _
b0 ^
0]
b0 \
0[
0Z
0Y
bx X
bx W
0V
0U
b0 T
b0 S
b0 R
1Q
1P
b0 O
b0 N
b0 M
b0 L
bx K
b0 J
0I
b0 H
b0 G
b0 F
b0 E
bx D
b0 C
0B
bx A
b0 @
b0 ?
bx >
b0 =
b0 <
b100 ;
b100 :
b100 9
bx 8
bx 7
bx 6
05
04
03
x2
x1
bx 0
bx /
bx .
b0 -
b0 ,
0+
0*
b0 )
bx (
0'
0&
0%
b0 $
bx #
1"
1!
$end
#10
1]
1Y
b101 `
1[
b101 a
b101 b
13
b101 9
15
b101 :
b101 ;
b1 G
b1 N
b1 j
x'
b1 m
x&
b1 E
b1 L
1%
#20
0%
#30
b10 N
b0 K
b0x000 J
b10 G
b0 D
b0x000 C
b110 ;
b110 :
b110 9
b110 b
b110 a
b110 `
b10 L
b10 E
b10 m
b10 j
1%
#40
0%
#50
b111 `
b111 a
b111 b
b111 9
b111 :
b111 ;
b0xx00 C
b11 G
b0xx00 J
b11 N
b11 j
b11 m
b11 E
b11 L
1%
#60
0%
#70
b100 N
b0xxx0 J
b100 G
b0xxx0 C
b0 ;
b1000 :
b1000 9
b0 b
b1000 a
b1000 `
b100 L
b100 E
b100 m
b100 j
1%
#80
0%
#90
b10111100 k
b10111100 n
02
01
b1001 `
0[
b1001 a
1Z
b1 b
b1001 9
05
b1001 :
14
b1 ;
b0xxxx C
b101 G
b0xxxx J
b101 N
b101 j
b101 m
b101 E
b101 L
1%
#100
0%
#110
b110 N
b1000xxxx J
b110 G
b1000xxxx C
b10 ;
b1010 :
b1010 9
b10 b
b1010 a
b1010 `
b110 L
b110 E
b110 m
1&
b110 j
1'
1%
#120
0%
#130
b1011 `
b1011 a
b11 b
b1011 9
b1011 :
b11 ;
b1100xxxx C
b111 G
b1100xxxx J
b111 N
b111 j
0'
b111 m
0&
b111 E
b111 L
1%
#140
0%
#150
b0 N
b1110xxxx J
b0 G
b1110xxxx C
b100 ;
b1100 :
b1100 9
b100 b
b1100 a
b1100 `
b0 L
b0 E
b0 m
1&
b0 j
1'
1%
#160
0%
#170
b1101 `
b1101 a
0Z
b101 b
b1101 9
b1101 :
04
b101 ;
b1111xxxx C
b1 G
b1111xxxx J
b1 N
b1 j
b1 m
b1 E
b1 L
1%
#180
0%
#190
b10 N
b1111xxxx K
b11111xxx J
b10 G
b1111xxxx D
b11111xxx C
b110 ;
b1110 :
b1110 9
b110 b
b1110 a
b1110 `
b10 L
b10 E
b10 m
b10 j
1%
#200
0%
#210
b1111 `
b1111 a
b111 b
b1111 9
b1111 :
b111 ;
b111111xx C
b11 G
b111111xx J
b11 N
b11 j
b11 m
b11 E
b11 L
1%
#220
0%
#230
b100 N
b1111110x J
b100 G
b1111110x C
b0 ;
b0 :
b10000 9
b0 b
b0 a
b10000 `
b100 L
b100 E
b100 m
0&
b100 j
0'
1%
#240
0%
#250
b0 #
b0 (
b0 0
b0 8
b0 o
0!
0]
0Y
b10001 `
1[
b1 a
1Z
b1 b
03
b10001 9
15
b1 :
14
b1 ;
b11111100 C
b101 G
b11111100 J
b101 N
b101 j
b101 m
b101 E
b101 L
1%
#260
0%
#270
b110 N
b110 G
b10 ;
b10 :
b10010 9
b10 b
b10 a
b10010 `
b110 L
b110 E
b110 m
1&
b110 j
1'
1%
#280
0%
#290
b10011 `
b11 a
b11 b
b10011 9
b11 :
b11 ;
b111 G
b111 N
b111 j
0'
b111 m
0&
b111 E
b111 L
1%
#300
0%
#310
b0 N
b0 G
b100 ;
b100 :
b10100 9
b100 b
b100 a
b10100 `
b0 L
b0 E
b0 m
1&
b0 j
1'
1%
#320
0%
1p
#330
b10101 `
b101 a
0Z
b101 b
b10101 9
b101 :
04
b101 ;
b1 G
b1 N
b1 j
b1 m
b1 E
b1 L
1%
#340
0%
#350
b10 N
b11111100 K
b10 G
b11111100 D
b110 ;
b110 :
b10110 9
b110 b
b110 a
b10110 `
b10 L
b10 E
b10 m
b10 j
1%
#360
0%
#370
b10111 `
b111 a
b111 b
b10111 9
b111 :
b111 ;
b11 G
b11 N
b11 j
b11 m
b11 E
b11 L
1%
#380
0%
#390
b100 N
b100 G
b0 ;
b1000 :
b11000 9
b0 b
b1000 a
b11000 `
b100 L
b100 E
b100 m
0&
b100 j
0'
1%
#400
0%
#410
b11001 `
0[
b1001 a
1Z
b1 b
b11001 9
05
b1001 :
14
b1 ;
b101 G
b101 N
b101 j
b101 m
b101 E
b101 L
1%
#420
0%
#430
b110 N
b110 G
b10 ;
b1010 :
b11010 9
b10 b
b1010 a
b11010 `
b110 L
b110 E
b110 m
1&
b110 j
1'
1%
#440
0%
#450
b11011 `
b1011 a
b11 b
b11011 9
b1011 :
b11 ;
b111 G
b111 N
b111 j
0'
b111 m
0&
b111 E
b111 L
1%
#460
0%
#470
b0 N
b0 G
b100 ;
b1100 :
b11100 9
b100 b
b1100 a
b11100 `
b0 L
b0 E
b0 m
1&
b0 j
1'
1%
#480
0%
#490
b11101 `
b1101 a
0Z
b101 b
b11101 9
b1101 :
04
b101 ;
b1 G
b1 N
b1 j
b1 m
b1 E
b1 L
1%
#500
0%
#510
b10 N
b10 G
b110 ;
b1110 :
b11110 9
b110 b
b1110 a
b11110 `
b10 L
b10 E
b10 m
b10 j
1%
#520
0%
#530
b11111 `
b1111 a
b111 b
b11111 9
b1111 :
b111 ;
b11 G
b11 N
b11 j
b11 m
b11 E
b11 L
1%
#540
0%
#550
b100 N
b100 G
b0 ;
b0 :
b0 9
b0 b
b0 a
b0 `
b100 L
b100 E
b100 m
0&
b100 j
0'
1%
#560
0%
#570
b11111111111111111111111111111111 S
b11111111111111111111111111111111 ^
b11111111111111111111111111111111 c
1]
1Y
b1 `
1[
b1 a
1Z
b1 b
13
b1 9
15
b1 :
14
b1 ;
b101 G
b101 N
b11111111111111111111111111111111 $
b11111111111111111111111111111111 )
b11111111111111111111111111111111 T
b11111111111111111111111111111111 \
b11111111111111111111111111111111 q
b101 j
b101 m
b101 E
b101 L
1%
#580
0%
#590
b110 N
b110 G
b10 ;
b10 :
b10 9
b10 b
b10 a
b10 `
b110 L
b110 E
b110 m
1&
b110 j
1'
1%
#600
0%
