Serial-paralelo/probador_s2p.v
module probador_s2p(
    output reg clk_32f, 
    output reg clk_4f,
    output reg data_in,//en paralelo serial se llama active_serial_paraleloTX
    input wire [7:0] data_out,
    input wire valid_out
);
    initial begin
      $dumpfile("serial_paralelo.vcd");
      $dumpvars;
    //start here
    
    @(posedge clk_32f);//Encima de (0)
      {data_in} <= 1;
    @(posedge clk_32f);
      {data_in} <= 0;
    @(posedge clk_32f);
      {data_in} <= 1;
    @(posedge clk_32f);
      {data_in} <= 1;
    @(posedge clk_32f);
      {data_in} <= 1;
    @(posedge clk_32f);
      {data_in} <= 1;
    @(posedge clk_32f);
      {data_in} <= 0;
    @(posedge clk_32f);
      {data_in} <= 0;
    //el que esta arriba de 0xBC(1)
    @(posedge clk_32f);
      {data_in} <= 1;
    @(posedge clk_32f);
      {data_in} <= 0;
    @(posedge clk_32f);
      {data_in} <= 1;
    @(posedge clk_32f);
      {data_in} <= 1;
    @(posedge clk_32f);
      {data_in} <= 1;
    @(posedge clk_32f);
      {data_in} <= 1;
    @(posedge clk_32f);
      {data_in} <= 0;
    @(posedge clk_32f);
      {data_in} <= 0;
    //encima de 0XBC(2)
        @(posedge clk_32f);
      {data_in} <= 1;
    @(posedge clk_32f);
      {data_in} <= 0;
    @(posedge clk_32f);
      {data_in} <= 1;
    @(posedge clk_32f);
      {data_in} <= 1;
    @(posedge clk_32f);
      {data_in} <= 1;
    @(posedge clk_32f);
      {data_in} <= 1;
    @(posedge clk_32f);
      {data_in} <= 0;
    @(posedge clk_32f);
      {data_in} <= 0;
    //encima de (3)
    @(posedge clk_32f);
      {data_in} <= 1;
    @(posedge clk_32f);
      {data_in} <= 0;
    @(posedge clk_32f);
      {data_in} <= 1;
    @(posedge clk_32f);
      {data_in} <= 1;
    @(posedge clk_32f);
      {data_in} <= 1;
    @(posedge clk_32f);
      {data_in} <= 1;
    @(posedge clk_32f);
      {data_in} <= 0;
    @(posedge clk_32f);
      {data_in} <= 0;
    
    //xd2
    @(posedge clk_32f);
      {data_in} <= 1;
    @(posedge clk_32f);
      {data_in} <= 1;
    @(posedge clk_32f);
      {data_in} <= 1;
    @(posedge clk_32f);
      {data_in} <= 1;
    @(posedge clk_32f);
      {data_in} <= 1;
    @(posedge clk_32f);
      {data_in} <= 1;
    @(posedge clk_32f);
      {data_in} <= 1;
    @(posedge clk_32f);
      {data_in} <= 1;
    //xd
    @(posedge clk_32f);
      {data_in} <= 1;
    @(posedge clk_32f);
      {data_in} <= 1;
    @(posedge clk_32f);
      {data_in} <= 1;
    @(posedge clk_32f);
      {data_in} <= 0;
    @(posedge clk_32f);
      {data_in} <= 1;
    @(posedge clk_32f);
      {data_in} <= 1;
    @(posedge clk_32f);
      {data_in} <= 1;
    @(posedge clk_32f);
      {data_in} <= 0;
    //xd 
    @(posedge clk_32f);
      {data_in} <= 1;
    @(posedge clk_32f);
      {data_in} <= 0;
    @(posedge clk_32f);
      {data_in} <= 1;
    @(posedge clk_32f);
      {data_in} <= 1;
    @(posedge clk_32f);
      {data_in} <= 1;
    @(posedge clk_32f);
      {data_in} <= 1;
    @(posedge clk_32f);
      {data_in} <= 0;
    @(posedge clk_32f);
      {data_in} <= 0;
    #300 $finish;
    end
    initial data_in <=1'b0;
    initial clk_32f <= 0;
	always #2 clk_32f <= ~clk_32f;

	initial clk_4f <= 0;
	always #4 clk_4f <= ~clk_4f;
endmodule

phy_rx/serial_paralelo.v
 /* ***********************************************************
                    Universidad de Costa Rica
                 Escuela de Ingenieria Electrica
                            IE-0323
                      Circuitos Digitales 1

                        serial_paralelo.v

Descripcion:
  

*********************************************************** */

module serial_paralelo(
	//ENTRADAS
			
			input data_in,			//entrada de datos
			input clk_32f,			//clock frecuencia 32
			input clk_4f,			//clock frecuencia 4
	//SALIDAS
	
			output reg	[7:0] data_out, 	//salida de datos	
			output reg  valid_out			//valid
						
);
			reg [7:0] buffer = 0;					//guarda datos actuales (n)
			reg [7:0] buffer_pasado;		//guarda datos pasados (n-1)
			reg active =1'b0; //active
			integer contador = 0;					//
			integer contador_BC = 0;				//contador de datos BC entrada*se buscan 4
	initial begin
	data_out <= 8'b00000000;
	valid_out <= 1'b0;
	end
	
	always @(posedge clk_32f)
	
	begin
			
				buffer <= {buffer[6:0], data_in};	//en buffer se concatena al ultimo bit de posicion el dato se va llenando de esta manera 
				
				if (contador_BC == 4 && contador == 1)
				begin
					
					active <= 1;
					
					if (buffer != 8'hBC)
					
					begin
						
						valid_out	<= 1;
						data_out <= buffer;
					end
					
					else if (buffer_pasado != 8'hBC && buffer == 8'hBC)
					
					begin
						
						valid_out	<= 0;
						contador_BC <= 0;
						data_out <= 0;//modificacion
						
					end
			end
				
				if (contador_BC < 4 && buffer == 8'hBC)
				
				begin
					
						valid_out	<= 0;
						data_out <= 0;
						contador_BC <= contador_BC + 1;
				end
					
				if (contador == 1)
				begin
						buffer_pasado <=buffer;
				end
				
				if (contador == 7)
				begin
						contador <= 0;
				end
				
				else if (contador != 7)
				begin
						contador <= contador + 1;
				end
		
	end
endmodule

Serial-paralelo/tests2p.v
`timescale 1s/1s
`include "serial_paralelo.v"
`include "probador_s2p.v"
module paralelo_serial_tb;
    wire clk_32f; 
    wire clk_4f; 
    wire data_in;
    wire [7:0] data_out;
    wire valid_out;
 

    serial_paralelo serial_paralelo(/*AUTOINST*/
				    // Outputs
				    .data_out		(data_out[7:0]),
				    .valid_out		(valid_out),
				    // Inputs
				    .data_in		(data_in),
				    .clk_32f		(clk_32f),
				    .clk_4f		(clk_4f));
    probador_s2p probador_s2p(/*AUTOINST*/
			      // Outputs
			      .clk_32f		(clk_32f),
			      .clk_4f		(clk_4f),
			      .data_in		(data_in),
			      // Inputs
			      .data_out		(data_out[7:0]),
			      .valid_out	(valid_out));
endmodule

Avance 2/serial_paralelo.vcd
$date
	Fri Oct 22 22:22:03 2021
$end
$version
	Icarus Verilog
$end
$timescale
	1s
$end
$scope module paralelo_serial_tb $end
$var wire 1 ! valid_out $end
$var wire 8 " data_out [7:0] $end
$var wire 1 # data_in $end
$var wire 1 $ clk_4f $end
$var wire 1 % clk_32f $end
$scope module probador_s2p $end
$var wire 1 ! valid_out $end
$var wire 8 & data_out [7:0] $end
$var reg 1 % clk_32f $end
$var reg 1 $ clk_4f $end
$var reg 1 # data_in $end
$upscope $end
$scope module serial_paralelo $end
$var wire 1 % clk_32f $end
$var wire 1 $ clk_4f $end
$var wire 1 # data_in $end
$var reg 1 ' active $end
$var reg 8 ( buffer [7:0] $end
$var reg 8 ) buffer_pasado [7:0] $end
$var reg 8 * data_out [7:0] $end
$var reg 1 ! valid_out $end
$var integer 32 + contador [31:0] $end
$var integer 32 , contador_BC [31:0] $end
$upscope $end
$upscope $end
$enddefinitions $end
#0
$dumpvars
b0 ,
b0 +
b0 *
bx )
b0 (
0'
b0 &
0%
0$
0#
b0 "
0!
$end
#2
b1 +
1#
1%
#4
0%
1$
#6
0#
b10 +
b0 )
b1 (
1%
#8
0%
0$
#10
b11 +
b10 (
1#
1%
#12
0%
1$
#14
b100 +
b101 (
1%
#16
0%
0$
#18
b101 +
b1011 (
1%
#20
0%
1$
#22
b110 +
b10111 (
1%
#24
0%
0$
#26
b111 +
b101111 (
0#
1%
#28
0%
1$
#30
b0 +
b1011110 (
1%
#32
0%
0$
#34
b1 +
b10111100 (
1#
1%
#36
0%
1$
#38
0#
b10 +
b10111100 )
b1 ,
b1111001 (
1%
#40
0%
0$
#42
b11 +
b11110010 (
1#
1%
#44
0%
1$
#46
b100 +
b11100101 (
1%
#48
0%
0$
#50
b101 +
b11001011 (
1%
#52
0%
1$
#54
b110 +
b10010111 (
1%
#56
0%
0$
#58
b111 +
b101111 (
0#
1%
#60
0%
1$
#62
b0 +
b1011110 (
1%
#64
0%
0$
#66
b1 +
b10111100 (
1#
1%
#68
0%
1$
#70
0#
b10 +
b10 ,
b1111001 (
1%
#72
0%
0$
#74
b11 +
b11110010 (
1#
1%
#76
0%
1$
#78
b100 +
b11100101 (
1%
#80
0%
0$
#82
b101 +
b11001011 (
1%
#84
0%
1$
#86
b110 +
b10010111 (
1%
#88
0%
0$
#90
b111 +
b101111 (
0#
1%
#92
0%
1$
#94
b0 +
b1011110 (
1%
#96
0%
0$
#98
b1 +
b10111100 (
1#
1%
#100
0%
1$
#102
0#
b10 +
b11 ,
b1111001 (
1%
#104
0%
0$
#106
b11 +
b11110010 (
1#
1%
#108
0%
1$
#110
b100 +
b11100101 (
1%
#112
0%
0$
#114
b101 +
b11001011 (
1%
#116
0%
1$
#118
b110 +
b10010111 (
1%
#120
0%
0$
#122
b111 +
b101111 (
0#
1%
#124
0%
1$
#126
b0 +
b1011110 (
1%
#128
0%
0$
#130
b1 +
b10111100 (
1#
1%
#132
0%
1$
#134
b10 +
b100 ,
b1111001 (
1%
#136
0%
0$
#138
b11 +
b11110011 (
1%
#140
0%
1$
#142
b100 +
b11100111 (
1%
#144
0%
0$
#146
b101 +
b11001111 (
1%
#148
0%
1$
#150
b110 +
b10011111 (
1%
#152
0%
0$
#154
b111 +
b111111 (
1%
#156
0%
1$
#158
b0 +
b1111111 (
1%
#160
0%
0$
#162
b1 +
b11111111 (
1%
#164
0%
1$
#166
b10 +
b11111111 )
b11111111 "
b11111111 &
b11111111 *
1!
1'
1%
#168
0%
0$
#170
b11 +
1%
#172
0%
1$
#174
0#
b100 +
1%
#176
0%
0$
#178
b101 +
b11111110 (
1#
1%
#180
0%
1$
#182
b110 +
b11111101 (
1%
#184
0%
0$
#186
b111 +
b11111011 (
1%
#188
0%
1$
#190
0#
b0 +
b11110111 (
1%
#192
0%
0$
#194
b1 +
b11101110 (
1#
1%
#196
0%
1$
#198
0#
b10 +
b11101110 )
b11101110 "
b11101110 &
b11101110 *
b11011101 (
1%
#200
0%
0$
#202
b11 +
b10111010 (
1#
1%
#204
0%
1$
#206
b100 +
b1110101 (
1%
#208
0%
0$
#210
b101 +
b11101011 (
1%
#212
0%
1$
#214
b110 +
b11010111 (
1%
#216
0%
0$
#218
b111 +
b10101111 (
0#
1%
#220
0%
1$
#222
b0 +
b1011110 (
1%
#224
0%
0$
#226
b1 +
b10111100 (
1%
#228
0%
1$
#230
b10 +
b10111100 )
b0 "
b0 &
b0 *
b0 ,
0!
b1111000 (
1%
#232
0%
0$
#234
b11 +
b11110000 (
1%
#236
0%
1$
#238
b100 +
b11100000 (
1%
#240
0%
0$
#242
b101 +
b11000000 (
1%
#244
0%
1$
#246
b110 +
b10000000 (
1%
#248
0%
0$
#250
b111 +
b0 (
1%
#252
0%
1$
#254
b0 +
1%
#256
0%
0$
#258
b1 +
1%
#260
0%
1$
#262
b10 +
b0 )
1%
#264
0%
0$
#266
b11 +
1%
#268
0%
1$
#270
b100 +
1%
#272
0%
0$
#274
b101 +
1%
#276
0%
1$
#278
b110 +
1%
#280
0%
0$
#282
b111 +
1%
#284
0%
1$
#286
b0 +
1%
#288
0%
0$
#290
b1 +
1%
#292
0%
1$
#294
b10 +
1%
#296
0%
0$
#298
b11 +
1%
#300
0%
1$
#302
b100 +
1%
#304
0%
0$
#306
b101 +
1%
#308
0%
1$
#310
b110 +
1%
#312
0%
0$
#314
b111 +
1%
#316
0%
1$
#318
b0 +
1%
#320
0%
0$
#322
b1 +
1%
#324
0%
1$
#326
b10 +
1%
#328
0%
0$
#330
b11 +
1%
#332
0%
1$
#334
b100 +
1%
#336
0%
0$
#338
b101 +
1%
#340
0%
1$
#342
b110 +
1%
#344
0%
0$
#346
b111 +
1%
#348
0%
1$
#350
b0 +
1%
#352
0%
0$
#354
b1 +
1%
#356
0%
1$
#358
b10 +
1%
#360
0%
0$
#362
b11 +
1%
#364
0%
1$
#366
b100 +
1%
#368
0%
0$
#370
b101 +
1%
#372
0%
1$
#374
b110 +
1%
#376
0%
0$
#378
b111 +
1%
#380
0%
1$
#382
b0 +
1%
#384
0%
0$
#386
b1 +
1%
#388
0%
1$
#390
b10 +
1%
#392
0%
0$
#394
b11 +
1%
#396
0%
1$
#398
b100 +
1%
#400
0%
0$
#402
b101 +
1%
#404
0%
1$
#406
b110 +
1%
#408
0%
0$
#410
b111 +
1%
#412
0%
1$
#414
b0 +
1%
#416
0%
0$
#418
b1 +
1%
#420
0%
1$
#422
b10 +
1%
#424
0%
0$
#426
b11 +
1%
#428
0%
1$
#430
b100 +
1%
#432
0%
0$
#434
b101 +
1%
#436
0%
1$
#438
b110 +
1%
#440
0%
0$
#442
b111 +
1%
#444
0%
1$
#446
b0 +
1%
#448
0%
0$
#450
b1 +
1%
#452
0%
1$
#454
b10 +
1%
#456
0%
0$
#458
b11 +
1%
#460
0%
1$
#462
b100 +
1%
#464
0%
0$
#466
b101 +
1%
#468
0%
1$
#470
b110 +
1%
#472
0%
0$
#474
b111 +
1%
#476
0%
1$
#478
b0 +
1%
#480
0%
0$
#482
b1 +
1%
#484
0%
1$
#486
b10 +
1%
#488
0%
0$
#490
b11 +
1%
#492
0%
1$
#494
b100 +
1%
#496
0%
0$
#498
b101 +
1%
#500
0%
1$
#502
b110 +
1%
#504
0%
0$
#506
b111 +
1%
#508
0%
1$
#510
b0 +
1%
#512
0%
0$
#514
b1 +
1%
#516
0%
1$
#518
b10 +
1%
#520
0%
0$
#522
b11 +
1%
