phy/clock_generator.v
module clock_generator(
    input clk_32f,
    output reg clk_f,
    output reg clk_2f,
    output reg clk_4f
    );

    initial clk_f <= 0;
    initial clk_2f <= 0;
    initial clk_4f <= 0;
    
    reg [27:0] counter1 = 28'd4;
    reg [27:0] counter2 = 28'd4;
    reg [27:0] counter3 = 28'd4;
    parameter df_1 = 28'd32; //divisor de frecuencia
    parameter df_2 = 28'd16; //divisor de frecuencia
    parameter df_4 = 28'd8; //divisor de frecuencia

    always @(posedge clk_32f)
    begin
      counter1<= counter1 + 28'd1;
        if (counter1 >=(df_1-1))
            counter1 <= 28'd0;
            clk_f <= (counter1 <df_1/2)?1'b1:1'b0;
    end

    always @(posedge clk_32f)
    begin
      counter2 <= counter2 + 28'd1;
        if (counter2 >=(df_2-1))
            counter2 <= 28'd0;
            clk_2f <= (counter2 <df_2/2)?1'b1:1'b0;
    end
    
    always @(posedge clk_32f)
    begin
      counter3 <= counter3 + 28'd1;
        if (counter3 >=(df_4-1))
            counter3 <= 28'd0;
            clk_4f <= (counter3 <df_4/2)?1'b1:1'b0;
    end

    
endmodule

Paralelo-serial/Paralelo-serial/probador_paralelo_serial.v
// `include "clock_generator.v"

module probador_paralelo_serial( // Módulo probador: generador de señales y monitor de datos

    output reg clk_32f,
	output reg clk_4f,
	output reg valid_0,
    output reg [7:0] data_in, //salida de 8 bits
	input data_out); 

	// Generación cíclica de la señal reloj
	initial clk_32f <= 1;
	initial clk_4f <= 0;
	always	#1 clk_32f <= ~clk_32f; // Hace "toggle" cada 10ns
	always	#8 clk_4f <= ~clk_4f; // Hace "toggle" cada 10ns

    /* clock_generator test_clk(.clk_4f(clk_4f), .clk_32f(clk_32f)) */

	initial begin

		$dumpfile("paralelo_serial.vcd");	// Nombre de archivo del "dump"
		$dumpvars;// Directiva para "dumpear" todas las variables 

		valid_0 = 0;
        
		@(posedge clk_4f)	// Espera/sincroniza con el flanco positivo del reloj
		
		@(posedge clk_32f)
		valid_0 = 1;

		@(posedge clk_4f)
		data_in = 8'hFF;

		@(posedge clk_32f)

        @(posedge clk_4f)
        data_in = 8'hEE;

        @(posedge clk_4f)
		#15 $finish;

	end

endmodule

phy_tx/paralelo_serial.v
// Fecha: 20-10-2021
// Convertidor señal serial-paralelo
// Version 1.0

// Módulo con la lógica del convertidor de señales
module paralelo_serial (
    input clk_4f,
    input clk_32f,
    input valid_0,
    input [7:0] data_in,
    output reg data_out
);
    
    reg [7:0] data2send;            // Cable para almacenar la señal para la salida en 8 bits
    reg [2:0] contador = 3'b000;    // Contador para sincronizar salida data_out

    always @(posedge clk_4f) begin
    if (valid_0 == 1) begin
        data2send <= data_in;        // Asignar data_in a data2out
    end

    if (valid_0 == 0) begin
        data2send <= 8'hBC;         // En caso de que valid sea 0 se le asigna hex(BC)
    end

    end  

    

    always @(posedge clk_32f) begin         // Logica para convertir señal paralelo a serial
        case (contador)
            3'b100: data_out = data2send[7];
            3'b101: data_out = data2send[6];
            3'b110: data_out = data2send[5];
            3'b111: data_out = data2send[4];
            3'b000: data_out = data2send[3];
            3'b001: data_out = data2send[2];
            3'b010: data_out = data2send[1];
            3'b011: data_out = data2send[0];
            default: data_out = 1'b0;
        endcase
    
    contador = contador + 1;                // Aumentar el contador
    end


endmodule

Paralelo-serial/Paralelo-serial/banco_paralelo_serial.v
// `include "clock_generator.v"
`include "paralelo_serial.v"
`include "probador_paralelo_serial.v"

module banco_paralelo_serial;

    wire clk_4f;
    wire clk_32f;
    wire valid_0;
    wire [7:0] data_in;
    wire data_out;

    paralelo_serial conductual(.clk_4f(clk_4f), .clk_32f(clk_32f), .valid_0(valid_0), .data_in(data_in), .data_out(data_out));

    probador_paralelo_serial prob(.clk_4f(clk_4f), .clk_32f(clk_32f), .valid_0(valid_0), .data_in(data_in), .data_out(data_out));

endmodule

Paralelo-serial/Paralelo-serial/paralelo_serial.vcd
$date
	Thu Oct 21 17:44:43 2021
$end
$version
	Icarus Verilog
$end
$timescale
	1s
$end
$scope module banco_paralelo_serial $end
$var wire 1 ! valid_0 $end
$var wire 1 " data_out $end
$var wire 8 # data_in [7:0] $end
$var wire 1 $ clk_4f $end
$var wire 1 % clk_32f $end
$scope module conductual $end
$var wire 1 ! valid_0 $end
$var wire 8 & data_in [7:0] $end
$var wire 1 $ clk_4f $end
$var wire 1 % clk_32f $end
$var reg 3 ' contador [2:0] $end
$var reg 8 ( data2send [7:0] $end
$var reg 1 " data_out $end
$upscope $end
$scope module prob $end
$var wire 1 " data_out $end
$var reg 1 % clk_32f $end
$var reg 1 $ clk_4f $end
$var reg 8 ) data_in [7:0] $end
$var reg 1 ! valid_0 $end
$upscope $end
$upscope $end
$enddefinitions $end
#0
$dumpvars
bx )
bx (
b1 '
bx &
1%
0$
bx #
x"
0!
$end
#1
0%
#2
b10 '
1%
#3
0%
#4
b11 '
1%
#5
0%
#6
b100 '
1%
#7
0%
#8
b10111100 (
b101 '
1%
1$
#9
0%
#10
1!
b110 '
0"
1%
#11
0%
#12
b111 '
1"
1%
#13
0%
#14
b0 '
1%
#15
0%
#16
b1 '
1%
0$
#17
0%
#18
b10 '
1%
#19
0%
#20
b11 '
0"
1%
#21
0%
#22
b100 '
1%
#23
0%
#24
b11111111 (
b101 '
1"
b11111111 #
b11111111 &
b11111111 )
1%
1$
#25
0%
#26
b110 '
1%
#27
0%
#28
b111 '
1%
#29
0%
#30
b0 '
1%
#31
0%
#32
b1 '
1%
0$
#33
0%
#34
b10 '
1%
#35
0%
#36
b11 '
1%
#37
0%
#38
b100 '
1%
#39
0%
#40
b11101110 (
b101 '
b11101110 #
b11101110 &
b11101110 )
1%
1$
#41
0%
#42
b110 '
1%
#43
0%
#44
b111 '
1%
#45
0%
#46
b0 '
0"
1%
#47
0%
#48
b1 '
1"
1%
0$
#49
0%
#50
b10 '
1%
#51
0%
#52
b11 '
1%
#53
0%
#54
b100 '
0"
1%
#55
0%
#56
b101 '
1"
1%
1$
#57
0%
#58
b110 '
1%
#59
0%
#60
b111 '
1%
#61
0%
#62
b0 '
0"
1%
#63
0%
#64
b1 '
1"
1%
0$
#65
0%
#66
b10 '
1%
#67
0%
#68
b11 '
1%
#69
0%
#70
b100 '
0"
1%
