phy/clock_generator.v
module clock_generator(
    input clk_32f,
    output reg clk_f,
    output reg clk_2f,
    output reg clk_4f
    );

    initial clk_f <= 0;
    initial clk_2f <= 0;
    initial clk_4f <= 0;
    
    reg [27:0] counter1 = 28'd4;
    reg [27:0] counter2 = 28'd4;
    reg [27:0] counter3 = 28'd4;
    parameter df_1 = 28'd32; //divisor de frecuencia
    parameter df_2 = 28'd16; //divisor de frecuencia
    parameter df_4 = 28'd8; //divisor de frecuencia

    always @(posedge clk_32f)
    begin
      counter1<= counter1 + 28'd1;
        if (counter1 >=(df_1-1))
            counter1 <= 28'd0;
            clk_f <= (counter1 <df_1/2)?1'b1:1'b0;
    end

    always @(posedge clk_32f)
    begin
      counter2 <= counter2 + 28'd1;
        if (counter2 >=(df_2-1))
            counter2 <= 28'd0;
            clk_2f <= (counter2 <df_2/2)?1'b1:1'b0;
    end
    
    always @(posedge clk_32f)
    begin
      counter3 <= counter3 + 28'd1;
        if (counter3 >=(df_4-1))
            counter3 <= 28'd0;
            clk_4f <= (counter3 <df_4/2)?1'b1:1'b0;
    end

    
endmodule

Paralelo-serial/Paralelo-serial/probador_paralelo_serial.v
// `include "clock_generator.v"

module probador_paralelo_serial( // Módulo probador: generador de señales y monitor de datos

    output reg clk_32f,
	output reg clk_4f,
	output reg valid_0,
    output reg [7:0] data_in, //salida de 8 bits
	input data_out); 

	// Generación cíclica de la señal reloj
	initial clk_32f <= 0;
	initial clk_4f <= 0;
	always	#1 clk_32f <= ~clk_32f; // Hace "toggle" cada 10ns
	always	#8 clk_4f <= ~clk_4f; // Hace "toggle" cada 10ns

    /* clock_generator test_clk(.clk_4f(clk_4f), .clk_32f(clk_32f)) */

	initial begin

		$dumpfile("paralelo_serial.vcd");	// Nombre de archivo del "dump"
		$dumpvars;// Directiva para "dumpear" todas las variables 

		valid_0 = 0;

        
		$display("\tclk,\tValid_in,\tSenal_generada,\tSalida_modulo,\tValid_out");

		// Mensaje que se imprime en consola cada vez que un elemento de la lista cambia
		$monitor("\t%b", valid_0);
        


		@(posedge clk_4f)	// Espera/sincroniza con el flanco positivo del reloj
		data_in = 8'hFF;
		
		@(posedge clk_4f)
		valid_0 = 1;
        @(posedge clk_4f)
        @(posedge clk_4f)

        @(posedge clk_4f)
        data_in = 8'hEE;

        @(posedge clk_4f)
        @(posedge clk_4f)
        @(posedge clk_4f)


		@(posedge clk_4f)
		valid_0 = 0;

        @(posedge clk_4f)
        @(posedge clk_4f)
        @(posedge clk_4f)

        @(posedge clk_4f)
        data_in = 8'h7F;

        @(posedge clk_4f)
        @(posedge clk_4f)
        @(posedge clk_4f)
        data_in = 8'h03;
		@(posedge clk_4f)

		#15 $finish;

	end

endmodule

Paralelo-serial/Paralelo-serial/paralelo_serial.v
// Fecha: 20-10-2021
// Convertidor señal serial-paralelo
// Version 1.0

// Módulo con la lógica del convertidor de señales
module paralelo_serial (
    input clk_4f,
    input clk_32f,
    input valid_0,
    input [7:0] data_in,
    output reg data_out
);
    
    reg [7:0] data2send;            // Cable para almacenar la señal para la salida en 8 bits
    reg [1:0] contador = 3'b000;    // Contador para sincronizar salida data_out

    always @(posedge clk_4f) begin
    if (valid_0 == 1) begin
        data2send <= data_in;        // Asignar data_in a data2out
    end
        

    else begin
        data2send <= 8'hBC;          // En caso de que valid sea 0 se le asigna hex(BC)
    end

    data_out <= data2send;
        
    end

    always @(posedge clk_32f) begin         // Logica para convertir señal paralelo a serial
        case (contador)
            3'b000: data_out <= data2send[7];
            3'b001: data_out <= data2send[6];
            3'b010: data_out <= data2send[5];
            3'b011: data_out <= data2send[4];
            3'b100: data_out <= data2send[3];
            3'b101: data_out <= data2send[2];
            3'b110: data_out <= data2send[1];
            3'b111: data_out <= data2send[0];
            default: data_out <= 1'b0;
        endcase
    
    contador <= contador + 3'b001;                // Aumentar el contador
    end


endmodule

Paralelo-serial/Paralelo-serial/banco_paralelo_serial.v
// `include "clock_generator.v"
`include "paralelo_serial.v"
`include "probador_paralelo_serial.v"

module banco_paralelo_serial;

    wire clk_4f;
    wire clk_32f;
    wire valid_0;
    wire [7:0] data_in;
    wire data_out;

    paralelo_serial conductual(.clk_4f(clk_4f), .clk_32f(clk_32f), .valid_0(valid_0), .data_in(data_in), .data_out(data_out));

    probador_paralelo_serial prob(.clk_4f(clk_4f), .clk_32f(clk_32f), .valid_0(valid_0), .data_in(data_in), .data_out(data_out));

endmodule

Paralelo-serial/Paralelo-serial/paralelo_serial.vcd
$date
	Wed Oct 20 16:36:14 2021
$end
$version
	Icarus Verilog
$end
$timescale
	1s
$end
$scope module banco_paralelo_serial $end
$var wire 1 ! valid_0 $end
$var wire 1 " data_out $end
$var wire 8 # data_in [7:0] $end
$var wire 1 $ clk_4f $end
$var wire 1 % clk_32f $end
$scope module conductual $end
$var wire 1 ! valid_0 $end
$var wire 8 & data_in [7:0] $end
$var wire 1 $ clk_4f $end
$var wire 1 % clk_32f $end
$var reg 2 ' contador [1:0] $end
$var reg 8 ( data2send [7:0] $end
$var reg 1 " data_out $end
$upscope $end
$scope module prob $end
$var wire 1 " data_out $end
$var reg 1 % clk_32f $end
$var reg 1 $ clk_4f $end
$var reg 8 ) data_in [7:0] $end
$var reg 1 ! valid_0 $end
$upscope $end
$upscope $end
$enddefinitions $end
#0
$dumpvars
bx )
bx (
b0 '
bx &
0%
0$
bx #
x"
0!
$end
#1
b1 '
1%
#2
0%
#3
b10 '
1%
#4
0%
#5
b11 '
1%
#6
0%
#7
b0 '
1%
#8
b10111100 (
b11111111 #
b11111111 &
b11111111 )
0%
1$
#9
b1 '
1"
1%
#10
0%
#11
b10 '
0"
1%
#12
0%
#13
b11 '
1"
1%
#14
0%
#15
b0 '
1%
#16
0%
0$
#17
b1 '
1%
#18
0%
#19
b10 '
0"
1%
#20
0%
#21
b11 '
1"
1%
#22
0%
#23
b0 '
1%
#24
0"
1!
0%
1$
#25
b1 '
1"
1%
#26
0%
#27
b10 '
0"
1%
#28
0%
#29
b11 '
1"
1%
#30
0%
#31
b0 '
1%
#32
0%
0$
#33
b1 '
1%
#34
0%
#35
b10 '
0"
1%
#36
0%
#37
b11 '
1"
1%
#38
0%
#39
b0 '
1%
#40
0"
b11111111 (
0%
1$
#41
b1 '
1"
1%
#42
0%
#43
b10 '
1%
#44
0%
#45
b11 '
1%
#46
0%
#47
b0 '
1%
#48
0%
0$
#49
b1 '
1%
#50
0%
#51
b10 '
1%
#52
0%
#53
b11 '
1%
#54
0%
#55
b0 '
1%
#56
0%
1$
#57
b1 '
1%
#58
0%
#59
b10 '
1%
#60
0%
#61
b11 '
1%
#62
0%
#63
b0 '
1%
#64
0%
0$
#65
b1 '
1%
#66
0%
#67
b10 '
1%
#68
0%
#69
b11 '
1%
#70
0%
#71
b0 '
1%
#72
b11101110 (
b11101110 #
b11101110 &
b11101110 )
0%
1$
#73
b1 '
1%
#74
0%
#75
b10 '
1%
#76
0%
#77
b11 '
1%
#78
0%
#79
b0 '
0"
1%
#80
0%
0$
#81
b1 '
1"
1%
#82
0%
#83
b10 '
1%
#84
0%
#85
b11 '
1%
#86
0%
#87
b0 '
0"
1%
#88
0%
1$
#89
b1 '
1"
1%
#90
0%
#91
b10 '
1%
#92
0%
#93
b11 '
1%
#94
0%
#95
b0 '
0"
1%
#96
0%
0$
#97
b1 '
1"
1%
#98
0%
#99
b10 '
1%
#100
0%
#101
b11 '
1%
#102
0%
#103
b0 '
0"
1%
#104
0%
1$
#105
b1 '
1"
1%
#106
0%
#107
b10 '
1%
#108
0%
#109
b11 '
1%
#110
0%
#111
b0 '
0"
1%
#112
0%
0$
#113
b1 '
1"
1%
#114
0%
#115
b10 '
1%
#116
0%
#117
b11 '
1%
#118
0%
#119
b0 '
0"
1%
#120
0%
1$
#121
b1 '
1"
1%
#122
0%
#123
b10 '
1%
#124
0%
#125
b11 '
1%
#126
0%
#127
b0 '
0"
1%
#128
0%
0$
#129
b1 '
1"
1%
#130
0%
#131
b10 '
1%
#132
0%
#133
b11 '
1%
#134
0%
#135
b0 '
0"
1%
#136
b10111100 (
0!
0%
1$
#137
b1 '
1"
1%
#138
0%
#139
b10 '
0"
1%
#140
0%
#141
b11 '
1"
1%
#142
0%
#143
b0 '
1%
#144
0%
0$
#145
b1 '
1%
#146
0%
#147
b10 '
0"
1%
#148
0%
#149
b11 '
1"
1%
#150
0%
#151
b0 '
1%
#152
0"
0%
1$
#153
b1 '
1"
1%
#154
0%
#155
b10 '
0"
1%
#156
0%
#157
b11 '
1"
1%
#158
0%
#159
b0 '
1%
#160
0%
0$
#161
b1 '
1%
#162
0%
#163
b10 '
0"
1%
#164
0%
#165
b11 '
1"
1%
#166
0%
#167
b0 '
1%
#168
0"
0%
1$
#169
b1 '
1"
1%
#170
0%
#171
b10 '
0"
1%
#172
0%
#173
b11 '
1"
1%
#174
0%
#175
b0 '
1%
#176
0%
0$
#177
b1 '
1%
#178
0%
#179
b10 '
0"
1%
#180
0%
#181
b11 '
1"
1%
#182
0%
#183
b0 '
1%
#184
0"
0%
1$
#185
b1 '
1"
1%
#186
0%
#187
b10 '
0"
1%
#188
0%
#189
b11 '
1"
1%
#190
0%
#191
b0 '
1%
#192
0%
0$
#193
b1 '
1%
#194
0%
#195
b10 '
0"
1%
#196
0%
#197
b11 '
1"
1%
#198
0%
#199
b0 '
1%
#200
0"
b1111111 #
b1111111 &
b1111111 )
0%
1$
#201
b1 '
1"
1%
#202
0%
#203
b10 '
0"
1%
#204
0%
#205
b11 '
1"
1%
#206
0%
#207
b0 '
1%
#208
0%
0$
#209
b1 '
1%
#210
0%
#211
b10 '
0"
1%
#212
0%
#213
b11 '
1"
1%
#214
0%
#215
b0 '
1%
#216
0"
0%
1$
#217
b1 '
1"
1%
#218
0%
#219
b10 '
0"
1%
#220
0%
#221
b11 '
1"
1%
#222
0%
#223
b0 '
1%
#224
0%
0$
#225
b1 '
1%
#226
0%
#227
b10 '
0"
1%
#228
0%
#229
b11 '
1"
1%
#230
0%
#231
b0 '
1%
#232
0"
0%
1$
#233
b1 '
1"
1%
#234
0%
#235
b10 '
0"
1%
#236
0%
#237
b11 '
1"
1%
#238
0%
#239
b0 '
1%
#240
0%
0$
#241
b1 '
1%
#242
0%
#243
b10 '
0"
1%
#244
0%
#245
b11 '
1"
1%
#246
0%
#247
b0 '
1%
#248
0"
b11 #
b11 &
b11 )
0%
1$
#249
b1 '
1"
1%
#250
0%
#251
b10 '
0"
1%
#252
0%
#253
b11 '
1"
1%
#254
0%
#255
b0 '
1%
#256
0%
0$
#257
b1 '
1%
#258
0%
#259
b10 '
0"
1%
#260
0%
#261
b11 '
1"
1%
#262
0%
#263
b0 '
1%
#264
0"
0%
1$
#265
b1 '
1"
1%
#266
0%
#267
b10 '
0"
1%
#268
0%
#269
b11 '
1"
1%
#270
0%
#271
b0 '
1%
#272
0%
0$
#273
b1 '
1%
#274
0%
#275
b10 '
0"
1%
#276
0%
#277
b11 '
1"
1%
#278
0%
#279
b0 '
1%
